Workbook

Sheet Léeme
A1: Estructura inicial de contenido · IA generativa para entornos laborales
A2: Curso e-learning asincrónico · 88 h · 6 módulos · 22 aprendizajes esperados · diseño propio, PF1823 solo como referencia
A4: Qué es | B4: Estructura base del curso: módulo → competencia → aprendizaje esperado (AE) → contenidos (saber / saber hacer / saber ser) → técnica metodológica → recursos (Rise, quizzes, casos, hitos del proyecto, foro, videos, evaluaciones). Sirve de insumo para guiones de video, infografías y páginas de Rise.
A5: Audiencia | B5: Pensado para personas cesantes o en búsqueda de empleo como público principal, y que también sirva a quienes ya trabajan y quieren sumar IA. Un solo diseño para ambos: el proyecto parte de un «desafío laboral real», definido como una tarea de un cargo que la persona ejerce hoy o al que aspira (tomada de una oferta real). Los casos y ejemplos usan situaciones laborales comunes, sin suponer un empleo actual ni licencias corporativas: se priorizan herramientas gratuitas o con plan gratuito y uso desde celular. | C5: Solo en personas que estén trabajando. Está orientado a personas que usen IA en temas administrativos y de productividad en el trabajo.
A6: Normativa base | B6: RE 2.484 de 19-10-2026 (Instructivo FT), leída íntegra: ver hoja «Cumplimiento RE 2484», que cruza cada exigencia con este diseño. Importante: la RE remite los criterios, indicadores y medios de verificación de la evaluación técnica a un «Anexo Técnico» y a una «Guía Técnica» que NO vienen en el documento y que aún no están publicados en sence.cl. Mientras no los tengamos, no es posible asegurar la aprobación a la primera; ver «Pendientes».
A7: Estado | B7: BORRADOR de trabajo. Los 22 AE y las 6 competencias están diseñados para ser pertinentes a los módulos y temas de la propuesta a Accenture. PF1823 es solo una referencia: no se exige que coincidan con él. Aún NO se estructuró bajo la nueva normativa SENCE (RE 2.484): eso viene después, con el texto completo publicado.
A8: Modelo de tiempos | B8: 1 pantalla de Rise = 7,5 min · quiz formativo = 15 min por tema · foro = 30 min por módulo · videos de bienvenida y de resumen = 3 min cada uno · caso o hito de proyecto = 1,5 h. Todos son parámetros editables en la hoja «Parámetros»; el resto se recalcula.
A9: Criterio de diseño | B9: 1 tema = 1 AE = 1 Rise + 1 quiz formativo. Máximo 4 AE por módulo. Cada AE se trabaja en al menos un caso o hito del proyecto y se mide en la evaluación sumativa del módulo (ver columna «Cobertura» en «Estructura»).
A10: Proyecto incremental | B10: Un solo proyecto aplicado crece módulo a módulo (hitos P1 a P6d) y culmina en el pitch/portafolio. Cada hito tiene retroalimentación del facilitador/tutor responsable: es la instancia obligatoria de interacción, retroalimentación o acompañamiento que exigen la Ley 21.850 (art. 29 N°1) y la RE 2.484 (IV.2.1 g), además de la evaluación (IV.2.1 h).
A11: Casos de aplicación | B11: Los nombres de empresas son CANDIDATOS reales y públicos. Ninguno está verificado todavía: antes de guionar hay que localizar la fuente primaria, citarla con fecha y no usar cifras sin respaldo. No se inventan empresas, citas ni resultados.
A12: Hojas | B12: Parámetros · Resumen horas · Estructura · Matriz coherencia · Recursos · Casos y proyecto · Evaluación · Cumplimiento RE 2484 · Pendientes
A13: Convención de color | B13: Azul (letra) = dato que puedes editar. Negro = fórmula o texto fijo. Encabezados en azul #0090F8. | C13: Empoderatech.com

Sheet Parámetros
A1: Parámetros del modelo de tiempos
A2: Edita los valores en azul; todas las horas se recalculan.
A4: Parámetro | B4: Descripción | C4: Valor | D4: Unidad
A5: Minutos por pantalla Rise | B5: Lectura reflexiva de una pantalla | C5: 7.5 | D5: min
A6: Quiz formativo por tema | B6: Duración de cada quiz automatizado | C6: 15 | D6: min
A7: Foro por módulo | B7: Participación guiada con tutor | C7: 30 | D7: min
A8: Video de bienvenida | B8: Por módulo | C8: 3 | D8: min
A9: Video de resumen | B9: Por módulo | C9: 3 | D9: min
A10: Caso o hito de proyecto | B10: Duración de cada bloque de aplicación | C10: 90 | D10: min
A11: Inducción + diagnóstica (M1) | B11: Inducción tecnológica-metodológica, guía del participante y evaluación diagnóstica | C11: 45 | D11: min
A12: Horas totales del curso | B12: Según propuesta / plan formativo | C12: 88 | D12: h
A13: Tolerancia por módulo | B13: Diferencia aceptable entre horas objetivo y diseñadas | C13: 15 | D13: min

Sheet Resumen horas
A1: Resumen y coherencia de horas por módulo (desglose horario)
A2: La RE 2.484 (IV.2.2 c) exige concordancia entre la duración total y el desglose horario. Todo en minutos, calculado desde «Recursos»; la diferencia debe ser 0.
A4: Módulo | B4: Nombre | C4: Horas objetivo | D4: Min objetivo | E4: Min Rise | F4: Min Quiz formativo | G4: Min Caso de aplicación | H4: Min Hito proyecto | I4: Min Foro | J4: Min Video | K4: Min Evaluación sumativa | L4: Min Inducción/Diagnóstica | M4: Min Resumen y glosario | N4: Min diseñados | O4: Diferencia (min) | P4: Pantallas Rise | Q4: N° AE | R4: ¿Coherente?
A5: 1 | B5: Introducción a la IA generativa y prompt básico | C5: 16 | D5: =C5*60 -> 960 | E5: =SUMIFS(Recursos!$G$5:$G$105,Recursos!$B$5:$B$105,$A5,Recursos!$D$5:$D$105,"Rise") -> 487.5 | F5: =SUMIFS(Recursos!$G$5:$G$105,Recursos!$B$5:$B$105,$A5,Recursos!$D$5:$D$105,"Quiz formativo") -> 60 | G5: =SUMIFS(Recursos!$G$5:$G$105,Recursos!$B$5:$B$105,$A5,Recursos!$D$5:$D$105,"Caso de aplicación") -> 180 | H5: =SUMIFS(Recursos!$G$5:$G$105,Recursos!$B$5:$B$105,$A5,Recursos!$D$5:$D$105,"Hito proyecto") -> 90 | I5: =SUMIFS(Recursos!$G$5:$G$105,Recursos!$B$5:$B$105,$A5,Recursos!$D$5:$D$105,"Foro") -> 30 | J5: =SUMIFS(Recursos!$G$5:$G$105,Recursos!$B$5:$B$105,$A5,Recursos!$D$5:$D$105,"Video") -> 6 | K5: =SUMIFS(Recursos!$G$5:$G$105,Recursos!$B$5:$B$105,$A5,Recursos!$D$5:$D$105,"Evaluación sumativa") -> 60 | L5: =SUMIFS(Recursos!$G$5:$G$105,Recursos!$B$5:$B$105,$A5,Recursos!$D$5:$D$105,"Inducción/Diagnóstica") -> 45 | M5: =SUMIFS(Recursos!$G$5:$G$105,Recursos!$B$5:$B$105,$A5,Recursos!$D$5:$D$105,"Resumen y glosario") -> 1.5 | N5: =SUM(E5:M5) -> 960 | O5: =D5-N5 -> 0 | P5: =SUMIFS(Estructura!$M$5:$M$26,Estructura!$B$5:$B$26,A5) -> 65 | Q5: =COUNTIFS(Estructura!$B$5:$B$26,A5) -> 4 | R5: =IF(AND(ROUND(O5,1)=0,Q5<=4),"OK","Revisar") -> OK
A6: 2 | B6: Comunicación y redacción profesional | C6: 16 | D6: =C6*60 -> 960 | E6: =SUMIFS(Recursos!$G$5:$G$105,Recursos!$B$5:$B$105,$A6,Recursos!$D$5:$D$105,"Rise") -> 532.5 | F6: =SUMIFS(Recursos!$G$5:$G$105,Recursos!$B$5:$B$105,$A6,Recursos!$D$5:$D$105,"Quiz formativo") -> 60 | G6: =SUMIFS(Recursos!$G$5:$G$105,Recursos!$B$5:$B$105,$A6,Recursos!$D$5:$D$105,"Caso de aplicación") -> 180 | H6: =SUMIFS(Recursos!$G$5:$G$105,Recursos!$B$5:$B$105,$A6,Recursos!$D$5:$D$105,"Hito proyecto") -> 90 | I6: =SUMIFS(Recursos!$G$5:$G$105,Recursos!$B$5:$B$105,$A6,Recursos!$D$5:$D$105,"Foro") -> 30 | J6: =SUMIFS(Recursos!$G$5:$G$105,Recursos!$B$5:$B$105,$A6,Recursos!$D$5:$D$105,"Video") -> 6 | K6: =SUMIFS(Recursos!$G$5:$G$105,Recursos!$B$5:$B$105,$A6,Recursos!$D$5:$D$105,"Evaluación sumativa") -> 60 | L6: =SUMIFS(Recursos!$G$5:$G$105,Recursos!$B$5:$B$105,$A6,Recursos!$D$5:$D$105,"Inducción/Diagnóstica") -> 0 | M6: =SUMIFS(Recursos!$G$5:$G$105,Recursos!$B$5:$B$105,$A6,Recursos!$D$5:$D$105,"Resumen y glosario") -> 1.5 | N6: =SUM(E6:M6) -> 960 | O6: =D6-N6 -> 0 | P6: =SUMIFS(Estructura!$M$5:$M$26,Estructura!$B$5:$B$26,A6) -> 71 | Q6: =COUNTIFS(Estructura!$B$5:$B$26,A6) -> 4 | R6: =IF(AND(ROUND(O6,1)=0,Q6<=4),"OK","Revisar") -> OK
A7: 3 | B7: Investigación y análisis de información | C7: 16 | D7: =C7*60 -> 960 | E7: =SUMIFS(Recursos!$G$5:$G$105,Recursos!$B$5:$B$105,$A7,Recursos!$D$5:$D$105,"Rise") -> 532.5 | F7: =SUMIFS(Recursos!$G$5:$G$105,Recursos!$B$5:$B$105,$A7,Recursos!$D$5:$D$105,"Quiz formativo") -> 60 | G7: =SUMIFS(Recursos!$G$5:$G$105,Recursos!$B$5:$B$105,$A7,Recursos!$D$5:$D$105,"Caso de aplicación") -> 180 | H7: =SUMIFS(Recursos!$G$5:$G$105,Recursos!$B$5:$B$105,$A7,Recursos!$D$5:$D$105,"Hito proyecto") -> 90 | I7: =SUMIFS(Recursos!$G$5:$G$105,Recursos!$B$5:$B$105,$A7,Recursos!$D$5:$D$105,"Foro") -> 30 | J7: =SUMIFS(Recursos!$G$5:$G$105,Recursos!$B$5:$B$105,$A7,Recursos!$D$5:$D$105,"Video") -> 6 | K7: =SUMIFS(Recursos!$G$5:$G$105,Recursos!$B$5:$B$105,$A7,Recursos!$D$5:$D$105,"Evaluación sumativa") -> 60 | L7: =SUMIFS(Recursos!$G$5:$G$105,Recursos!$B$5:$B$105,$A7,Recursos!$D$5:$D$105,"Inducción/Diagnóstica") -> 0 | M7: =SUMIFS(Recursos!$G$5:$G$105,Recursos!$B$5:$B$105,$A7,Recursos!$D$5:$D$105,"Resumen y glosario") -> 1.5 | N7: =SUM(E7:M7) -> 960 | O7: =D7-N7 -> 0 | P7: =SUMIFS(Estructura!$M$5:$M$26,Estructura!$B$5:$B$26,A7) -> 71 | Q7: =COUNTIFS(Estructura!$B$5:$B$26,A7) -> 4 | R7: =IF(AND(ROUND(O7,1)=0,Q7<=4),"OK","Revisar") -> OK
A8: 4 | B8: Contenido visual, sonoro y audiovisual | C8: 16 | D8: =C8*60 -> 960 | E8: =SUMIFS(Recursos!$G$5:$G$105,Recursos!$B$5:$B$105,$A8,Recursos!$D$5:$D$105,"Rise") -> 442.5 | F8: =SUMIFS(Recursos!$G$5:$G$105,Recursos!$B$5:$B$105,$A8,Recursos!$D$5:$D$105,"Quiz formativo") -> 60 | G8: =SUMIFS(Recursos!$G$5:$G$105,Recursos!$B$5:$B$105,$A8,Recursos!$D$5:$D$105,"Caso de aplicación") -> 270 | H8: =SUMIFS(Recursos!$G$5:$G$105,Recursos!$B$5:$B$105,$A8,Recursos!$D$5:$D$105,"Hito proyecto") -> 90 | I8: =SUMIFS(Recursos!$G$5:$G$105,Recursos!$B$5:$B$105,$A8,Recursos!$D$5:$D$105,"Foro") -> 30 | J8: =SUMIFS(Recursos!$G$5:$G$105,Recursos!$B$5:$B$105,$A8,Recursos!$D$5:$D$105,"Video") -> 6 | K8: =SUMIFS(Recursos!$G$5:$G$105,Recursos!$B$5:$B$105,$A8,Recursos!$D$5:$D$105,"Evaluación sumativa") -> 60 | L8: =SUMIFS(Recursos!$G$5:$G$105,Recursos!$B$5:$B$105,$A8,Recursos!$D$5:$D$105,"Inducción/Diagnóstica") -> 0 | M8: =SUMIFS(Recursos!$G$5:$G$105,Recursos!$B$5:$B$105,$A8,Recursos!$D$5:$D$105,"Resumen y glosario") -> 1.5 | N8: =SUM(E8:M8) -> 960 | O8: =D8-N8 -> 0 | P8: =SUMIFS(Estructura!$M$5:$M$26,Estructura!$B$5:$B$26,A8) -> 59 | Q8: =COUNTIFS(Estructura!$B$5:$B$26,A8) -> 4 | R8: =IF(AND(ROUND(O8,1)=0,Q8<=4),"OK","Revisar") -> OK
A9: 5 | B9: Automatización de tareas repetitivas | C9: 12 | D9: =C9*60 -> 720 | E9: =SUMIFS(Recursos!$G$5:$G$105,Recursos!$B$5:$B$105,$A9,Recursos!$D$5:$D$105,"Rise") -> 322.5 | F9: =SUMIFS(Recursos!$G$5:$G$105,Recursos!$B$5:$B$105,$A9,Recursos!$D$5:$D$105,"Quiz formativo") -> 45 | G9: =SUMIFS(Recursos!$G$5:$G$105,Recursos!$B$5:$B$105,$A9,Recursos!$D$5:$D$105,"Caso de aplicación") -> 180 | H9: =SUMIFS(Recursos!$G$5:$G$105,Recursos!$B$5:$B$105,$A9,Recursos!$D$5:$D$105,"Hito proyecto") -> 90 | I9: =SUMIFS(Recursos!$G$5:$G$105,Recursos!$B$5:$B$105,$A9,Recursos!$D$5:$D$105,"Foro") -> 30 | J9: =SUMIFS(Recursos!$G$5:$G$105,Recursos!$B$5:$B$105,$A9,Recursos!$D$5:$D$105,"Video") -> 6 | K9: =SUMIFS(Recursos!$G$5:$G$105,Recursos!$B$5:$B$105,$A9,Recursos!$D$5:$D$105,"Evaluación sumativa") -> 45 | L9: =SUMIFS(Recursos!$G$5:$G$105,Recursos!$B$5:$B$105,$A9,Recursos!$D$5:$D$105,"Inducción/Diagnóstica") -> 0 | M9: =SUMIFS(Recursos!$G$5:$G$105,Recursos!$B$5:$B$105,$A9,Recursos!$D$5:$D$105,"Resumen y glosario") -> 1.5 | N9: =SUM(E9:M9) -> 720 | O9: =D9-N9 -> 0 | P9: =SUMIFS(Estructura!$M$5:$M$26,Estructura!$B$5:$B$26,A9) -> 43 | Q9: =COUNTIFS(Estructura!$B$5:$B$26,A9) -> 3 | R9: =IF(AND(ROUND(O9,1)=0,Q9<=4),"OK","Revisar") -> OK
A10: 6 | B10: Taller de IA generativa para entornos laborales | C10: 12 | D10: =C10*60 -> 720 | E10: =SUMIFS(Recursos!$G$5:$G$105,Recursos!$B$5:$B$105,$A10,Recursos!$D$5:$D$105,"Rise") -> 217.5 | F10: =SUMIFS(Recursos!$G$5:$G$105,Recursos!$B$5:$B$105,$A10,Recursos!$D$5:$D$105,"Quiz formativo") -> 45 | G10: =SUMIFS(Recursos!$G$5:$G$105,Recursos!$B$5:$B$105,$A10,Recursos!$D$5:$D$105,"Caso de aplicación") -> 0 | H10: =SUMIFS(Recursos!$G$5:$G$105,Recursos!$B$5:$B$105,$A10,Recursos!$D$5:$D$105,"Hito proyecto") -> 360 | I10: =SUMIFS(Recursos!$G$5:$G$105,Recursos!$B$5:$B$105,$A10,Recursos!$D$5:$D$105,"Foro") -> 30 | J10: =SUMIFS(Recursos!$G$5:$G$105,Recursos!$B$5:$B$105,$A10,Recursos!$D$5:$D$105,"Video") -> 6 | K10: =SUMIFS(Recursos!$G$5:$G$105,Recursos!$B$5:$B$105,$A10,Recursos!$D$5:$D$105,"Evaluación sumativa") -> 60 | L10: =SUMIFS(Recursos!$G$5:$G$105,Recursos!$B$5:$B$105,$A10,Recursos!$D$5:$D$105,"Inducción/Diagnóstica") -> 0 | M10: =SUMIFS(Recursos!$G$5:$G$105,Recursos!$B$5:$B$105,$A10,Recursos!$D$5:$D$105,"Resumen y glosario") -> 1.5 | N10: =SUM(E10:M10) -> 720 | O10: =D10-N10 -> 0 | P10: =SUMIFS(Estructura!$M$5:$M$26,Estructura!$B$5:$B$26,A10) -> 29 | Q10: =COUNTIFS(Estructura!$B$5:$B$26,A10) -> 3 | R10: =IF(AND(ROUND(O10,1)=0,Q10<=4),"OK","Revisar") -> OK
A11: Total | C11: =SUM(C5:C10) -> 88 | D11: =SUM(D5:D10) -> 5280 | E11: =SUM(E5:E10) -> 2535 | F11: =SUM(F5:F10) -> 330 | G11: =SUM(G5:G10) -> 990 | H11: =SUM(H5:H10) -> 810 | I11: =SUM(I5:I10) -> 180 | J11: =SUM(J5:J10) -> 36 | ... Q11: =SUM(Q5:Q10) -> 22 | R11: =IF(AND(C11='Parámetros'!$C$12,COUNTIF(R5:R10,"OK")=6),"OK","Revisar") -> OK
A13: Distribución del tiempo por tipo de actividad (total curso)
A14: Tipo | C14: Horas | D14: % del total
A15: Rise | C15: =E11/60 -> 42.25 | D15: =C15/'Parámetros'!$C$12 -> 0.48011364
A16: Quiz formativo | C16: =F11/60 -> 5.5 | D16: =C16/'Parámetros'!$C$12 -> 0.0625
A17: Caso de aplicación | C17: =G11/60 -> 16.5 | D17: =C17/'Parámetros'!$C$12 -> 0.1875
A18: Hito proyecto | C18: =H11/60 -> 13.5 | D18: =C18/'Parámetros'!$C$12 -> 0.15340909
A19: Foro | C19: =I11/60 -> 3 | D19: =C19/'Parámetros'!$C$12 -> 0.034090909
A20: Video | C20: =J11/60 -> 0.6 | D20: =C20/'Parámetros'!$C$12 -> 0.0068181818
A21: Evaluación sumativa | C21: =K11/60 -> 5.75 | D21: =C21/'Parámetros'!$C$12 -> 0.065340909
A22: Inducción/Diagnóstica | C22: =L11/60 -> 0.75 | D22: =C22/'Parámetros'!$C$12 -> 0.0085227273
A23: Resumen y glosario | C23: =M11/60 -> 0.15 | D23: =C23/'Parámetros'!$C$12 -> 0.0017045455
A24: Total | C24: =SUM(C15:C23) -> 88 | D24: =SUM(D15:D23) -> 1
A26: Lectura: el tiempo se reparte entre estudio en Rise (≈48%) y aplicación con casos e hitos del proyecto (≈34%); el resto son quizzes, foros, videos y evaluaciones. El desglose suma exactamente las 88 h.

Sheet Estructura
A1: Estructura: módulo → competencia → aprendizaje esperado → contenidos → recursos
A2: Un AE por tema. Verbo de aplicación + objeto + condición. Ascenso taxonómico dentro de cada módulo. Diseño propio, pertinente a cada módulo y tema (PF1823 solo como referencia).
A4: ID AE | B4: Módulo | C4: Nombre del módulo | D4: Competencia del módulo | E4: Tema (propuesta) | F4: Aprendizaje esperado | G4: Nivel taxonómico (Bloom) | H4: Saber (conocimientos) | I4: Saber hacer (habilidades) | J4: Saber ser (actitudes) | K4: Técnica metodológica | L4: Rise asociado | M4: Pantallas Rise | N4: Min Rise | O4: Quiz formativo (15 min) | P4: N° Rise | Q4: N° Quiz | R4: N° Casos/Hitos | S4: N° Evaluaciones | T4: Cobertura
A5: M1-AE1 | B5: 1 | C5: Introducción a la IA generativa y prompt básico | D5: Interactuar con modelos de IA generativa mediante prompts efectivos y validación de resultados, para apoyar tareas de oficina de forma verificada. | E5: Fundamentos de IA generativa | F5: Explicar el funcionamiento general, los tipos y los límites de la IA generativa, ejemplificando sus usos en tareas laborales cotidianas. | G5: Comprender | H5: Qué es IA generativa; modelos de lenguaje, imagen y audio; tokens y contexto; límites (alucinación, sesgo, fecha de corte). | I5: Distinguir qué tareas laborales conviene o no delegar a un modelo generativo; probar un asistente con una tarea simple. | J5: Curiosidad crítica; apertura a un uso responsable de la tecnología. | K5: Exposición interactiva en Rise + ejemplos guiados | L5: Rise M1-T1 · Fundamentos de IA generativa | M5: 16 | N5: =M5*'Parámetros'!$C$5 -> 120 | O5: 8 ítems: conceptos, tipos de modelo y límites (opción múltiple, V/F con justificación) | P5: =COUNTIFS(Recursos!$F$5:$F$200,"*"&A5&"*",Recursos!$D$5:$D$200,"Rise") -> 1 | Q5: =COUNTIFS(Recursos!$F$5:$F$200,"*"&A5&"*",Recursos!$D$5:$D$200,"Quiz formativo") -> 1 | R5: =COUNTIFS(Recursos!$F$5:$F$200,"*"&A5&"*",Recursos!$D$5:$D$200,"Caso de aplicación")+COUNTIFS(Recursos!$F$5:$F$200,"*"&A5&"*",Recursos!$D$5:$D$200,"Hito proyecto") -> 1 | S5: =COUNTIFS(Recursos!$F$5:$F$200,"*"&A5&"*",Recursos!$D$5:$D$200,"Evaluación sumativa") -> 1 | T5: =IF(AND(P5>=1,Q5>=1,R5>=1,S5>=1),"OK","Revisar") -> OK
A6: M1-AE2 | B6: 1 | C6: Introducción a la IA generativa y prompt básico | D6: Interactuar con modelos de IA generativa mediante prompts efectivos y validación de resultados, para apoyar tareas de oficina de forma verificada. | E6: Prompts efectivos | F6: Formular prompts efectivos con rol, contexto, tarea y formato para obtener respuestas útiles en tareas laborales simples. | G6: Aplicar | H6: Estructura de un prompt (rol, contexto, tarea, formato, restricciones); errores frecuentes; iteración. | I6: Redactar y refinar prompts para resumir, reescribir y clasificar información de oficina; armar una biblioteca personal de prompts. | J6: Perseverancia en la iteración; orden y documentación del propio trabajo. | K6: Práctica guiada con ejemplos antes/después + laboratorio de prompts | L6: Rise M1-T2 · Prompts efectivos | M6: 16 | N6: =M6*'Parámetros'!$C$5 -> 120 | O6: 8 ítems: identificar componentes, ordenar pasos, elegir el mejor prompt entre variantes | P6: =COUNTIFS(Recursos!$F$5:$F$200,"*"&A6&"*",Recursos!$D$5:$D$200,"Rise") -> 1 | Q6: =COUNTIFS(Recursos!$F$5:$F$200,"*"&A6&"*",Recursos!$D$5:$D$200,"Quiz formativo") -> 1 | R6: =COUNTIFS(Recursos!$F$5:$F$200,"*"&A6&"*",Recursos!$D$5:$D$200,"Caso de aplicación")+COUNTIFS(Recursos!$F$5:$F$200,"*"&A6&"*",Recursos!$D$5:$D$200,"Hito proyecto") -> 2 | S6: =COUNTIFS(Recursos!$F$5:$F$200,"*"&A6&"*",Recursos!$D$5:$D$200,"Evaluación sumativa") -> 1 | T6: =IF(AND(P6>=1,Q6>=1,R6>=1,S6>=1),"OK","Revisar") -> OK
A7: M1-AE3 | B7: 1 | C7: Introducción a la IA generativa y prompt básico | D7: Interactuar con modelos de IA generativa mediante prompts efectivos y validación de resultados, para apoyar tareas de oficina de forma verificada. | E7: Parámetros de generación | F7: Ajustar parámetros de generación (temperatura, longitud, iteración) para adecuar las respuestas a distintos objetivos de una tarea. | G7: Aplicar | H7: Parámetros de generación y su efecto; relación creatividad–precisión; configuración según tarea. | I7: Comparar salidas de un mismo prompt con distintos parámetros y seleccionar la configuración más adecuada. | J7: Rigor al comparar y registrar resultados. | K7: Experimentación guiada (comparación de salidas) | L7: Rise M1-T3 · Parámetros de generación | M7: 16 | N7: =M7*'Parámetros'!$C$5 -> 120 | O7: 8 ítems: elegir parámetro según objetivo, interpretar salidas comparadas | P7: =COUNTIFS(Recursos!$F$5:$F$200,"*"&A7&"*",Recursos!$D$5:$D$200,"Rise") -> 1 | Q7: =COUNTIFS(Recursos!$F$5:$F$200,"*"&A7&"*",Recursos!$D$5:$D$200,"Quiz formativo") -> 1 | R7: =COUNTIFS(Recursos!$F$5:$F$200,"*"&A7&"*",Recursos!$D$5:$D$200,"Caso de aplicación")+COUNTIFS(Recursos!$F$5:$F$200,"*"&A7&"*",Recursos!$D$5:$D$200,"Hito proyecto") -> 1 | S7: =COUNTIFS(Recursos!$F$5:$F$200,"*"&A7&"*",Recursos!$D$5:$D$200,"Evaluación sumativa") -> 1 | T7: =IF(AND(P7>=1,Q7>=1,R7>=1,S7>=1),"OK","Revisar") -> OK
A8: M1-AE4 | B8: 1 | C8: Introducción a la IA generativa y prompt básico | D8: Interactuar con modelos de IA generativa mediante prompts efectivos y validación de resultados, para apoyar tareas de oficina de forma verificada. | E8: Validación de resultados | F8: Validar resultados generados por IA, contrastándolos con fuentes confiables, para detectar alucinaciones, errores y sesgos. | G8: Evaluar | H8: Tipos de error (alucinación, sesgo, desactualización); criterios de confiabilidad de fuentes; checklist de validación. | I8: Aplicar un checklist de validación a respuestas generadas y corregir o descartar lo no verificable. | J8: Responsabilidad profesional sobre lo que se firma o comparte; honestidad intelectual. | K8: Aprendizaje basado en casos reales (errores documentados) | L8: Rise M1-T4 · Validación de resultados | M8: 17 | N8: =M8*'Parámetros'!$C$5 -> 127.5 | O8: 8 ítems: detectar errores en respuestas dadas, decidir qué verificar y cómo | P8: =COUNTIFS(Recursos!$F$5:$F$200,"*"&A8&"*",Recursos!$D$5:$D$200,"Rise") -> 1 | Q8: =COUNTIFS(Recursos!$F$5:$F$200,"*"&A8&"*",Recursos!$D$5:$D$200,"Quiz formativo") -> 1 | R8: =COUNTIFS(Recursos!$F$5:$F$200,"*"&A8&"*",Recursos!$D$5:$D$200,"Caso de aplicación")+COUNTIFS(Recursos!$F$5:$F$200,"*"&A8&"*",Recursos!$D$5:$D$200,"Hito proyecto") -> 1 | S8: =COUNTIFS(Recursos!$F$5:$F$200,"*"&A8&"*",Recursos!$D$5:$D$200,"Evaluación sumativa") -> 1 | T8: =IF(AND(P8>=1,Q8>=1,R8>=1,S8>=1),"OK","Revisar") -> OK
A9: M2-AE1 | B9: 2 | C9: Comunicación y redacción profesional | D9: Optimizar la elaboración de documentos, presentaciones y planillas de cálculo con IA generativa, cuidando tono, audiencia y exactitud, en contextos laborales. | E9: Redacción y comunicación con IA | F9: Redactar correos, minutas e informes con apoyo de IA, ajustando tono, registro y audiencia. | G9: Aplicar | H9: Géneros de comunicación laboral; tono, registro y audiencia; rol de la IA como borrador. | I9: Producir y ajustar un correo, una minuta y un informe ejecutivo con IA, adaptando el mensaje a distintas audiencias. | J9: Cortesía y claridad en la comunicación profesional; responsabilidad sobre el mensaje. | K9: Práctica guiada con casos de comunicación laboral | L9: Rise M2-T1 · Redacción y comunicación con IA | M9: 18 | N9: =M9*'Parámetros'!$C$5 -> 135 | O9: 8 ítems: elegir tono/registro según audiencia, corregir borradores | P9: =COUNTIFS(Recursos!$F$5:$F$200,"*"&A9&"*",Recursos!$D$5:$D$200,"Rise") -> 1 | Q9: =COUNTIFS(Recursos!$F$5:$F$200,"*"&A9&"*",Recursos!$D$5:$D$200,"Quiz formativo") -> 1 | R9: =COUNTIFS(Recursos!$F$5:$F$200,"*"&A9&"*",Recursos!$D$5:$D$200,"Caso de aplicación")+COUNTIFS(Recursos!$F$5:$F$200,"*"&A9&"*",Recursos!$D$5:$D$200,"Hito proyecto") -> 2 | S9: =COUNTIFS(Recursos!$F$5:$F$200,"*"&A9&"*",Recursos!$D$5:$D$200,"Evaluación sumativa") -> 1 | T9: =IF(AND(P9>=1,Q9>=1,R9>=1,S9>=1),"OK","Revisar") -> OK
A10: M2-AE2 | B10: 2 | C10: Comunicación y redacción profesional | D10: Optimizar la elaboración de documentos, presentaciones y planillas de cálculo con IA generativa, cuidando tono, audiencia y exactitud, en contextos laborales. | E10: Prompting avanzado para textos | F10: Aplicar técnicas de prompting avanzado (ejemplos, restricciones, encadenamiento) para mejorar la calidad y consistencia de textos profesionales. | G10: Aplicar | H10: Few-shot, restricciones de estilo, encadenamiento de pasos, plantillas reutilizables. | I10: Diseñar plantillas de prompts reutilizables para comunicación profesional y evaluar su consistencia. | J10: Orden metodológico; mejora continua del propio proceso. | K10: Laboratorio de prompts con comparación de versiones | L10: Rise M2-T2 · Prompting avanzado para textos | M10: 18 | N10: =M10*'Parámetros'!$C$5 -> 135 | O10: 8 ítems: seleccionar técnica según problema, completar plantillas | P10: =COUNTIFS(Recursos!$F$5:$F$200,"*"&A10&"*",Recursos!$D$5:$D$200,"Rise") -> 1 | Q10: =COUNTIFS(Recursos!$F$5:$F$200,"*"&A10&"*",Recursos!$D$5:$D$200,"Quiz formativo") -> 1 | R10: =COUNTIFS(Recursos!$F$5:$F$200,"*"&A10&"*",Recursos!$D$5:$D$200,"Caso de aplicación")+COUNTIFS(Recursos!$F$5:$F$200,"*"&A10&"*",Recursos!$D$5:$D$200,"Hito proyecto") -> 1 | S10: =COUNTIFS(Recursos!$F$5:$F$200,"*"&A10&"*",Recursos!$D$5:$D$200,"Evaluación sumativa") -> 1 | T10: =IF(AND(P10>=1,Q10>=1,R10>=1,S10>=1),"OK","Revisar") -> OK
A11: M2-AE3 | B11: 2 | C11: Comunicación y redacción profesional | D11: Optimizar la elaboración de documentos, presentaciones y planillas de cálculo con IA generativa, cuidando tono, audiencia y exactitud, en contextos laborales. | E11: Presentaciones con IA | F11: Estructurar presentaciones de 6 láminas con apoyo de IA a partir de un mensaje clave y una audiencia definida. | G11: Aplicar | H11: Estructura narrativa de una presentación; relación mensaje–lámina; herramientas de IA para presentaciones. | I11: Generar esquema, contenido y guion de una presentación de 6 láminas y depurarla críticamente. | J11: Sentido de síntesis; cuidado de la imagen profesional. | K11: Taller práctico guiado (producto) | L11: Rise M2-T3 · Presentaciones con IA | M11: 17 | N11: =M11*'Parámetros'!$C$5 -> 127.5 | O11: 8 ítems: ordenar estructura narrativa, detectar láminas sobrecargadas | P11: =COUNTIFS(Recursos!$F$5:$F$200,"*"&A11&"*",Recursos!$D$5:$D$200,"Rise") -> 1 | Q11: =COUNTIFS(Recursos!$F$5:$F$200,"*"&A11&"*",Recursos!$D$5:$D$200,"Quiz formativo") -> 1 | R11: =COUNTIFS(Recursos!$F$5:$F$200,"*"&A11&"*",Recursos!$D$5:$D$200,"Caso de aplicación")+COUNTIFS(Recursos!$F$5:$F$200,"*"&A11&"*",Recursos!$D$5:$D$200,"Hito proyecto") -> 2 | S11: =COUNTIFS(Recursos!$F$5:$F$200,"*"&A11&"*",Recursos!$D$5:$D$200,"Evaluación sumativa") -> 1 | T11: =IF(AND(P11>=1,Q11>=1,R11>=1,S11>=1),"OK","Revisar") -> OK
A12: M2-AE4 | B12: 2 | C12: Comunicación y redacción profesional | D12: Optimizar la elaboración de documentos, presentaciones y planillas de cálculo con IA generativa, cuidando tono, audiencia y exactitud, en contextos laborales. | E12: Planillas de cálculo con IA | F12: Resolver análisis en planillas de cálculo con fórmulas generadas por IA, verificando su exactitud. | G12: Evaluar | H12: Fórmulas y funciones básicas; cómo pedir fórmulas a la IA; verificación con datos de prueba. | I12: Generar, aplicar y comprobar fórmulas, filtros y tablas con apoyo de IA en Sheets o Excel. | J12: Rigor numérico; desconfianza metódica ante resultados no comprobados. | K12: Resolución de problemas con datos de práctica | L12: Rise M2-T4 · Planillas de cálculo con IA | M12: 18 | N12: =M12*'Parámetros'!$C$5 -> 135 | O12: 8 ítems: interpretar fórmulas, detectar errores de referencia o de lógica | P12: =COUNTIFS(Recursos!$F$5:$F$200,"*"&A12&"*",Recursos!$D$5:$D$200,"Rise") -> 1 | Q12: =COUNTIFS(Recursos!$F$5:$F$200,"*"&A12&"*",Recursos!$D$5:$D$200,"Quiz formativo") -> 1 | R12: =COUNTIFS(Recursos!$F$5:$F$200,"*"&A12&"*",Recursos!$D$5:$D$200,"Caso de aplicación")+COUNTIFS(Recursos!$F$5:$F$200,"*"&A12&"*",Recursos!$D$5:$D$200,"Hito proyecto") -> 1 | S12: =COUNTIFS(Recursos!$F$5:$F$200,"*"&A12&"*",Recursos!$D$5:$D$200,"Evaluación sumativa") -> 1 | T12: =IF(AND(P12>=1,Q12>=1,R12>=1,S12>=1),"OK","Revisar") -> OK
A13: M3-AE1 | B13: 3 | C13: Investigación y análisis de información | D13: Acelerar la investigación y el análisis de información con herramientas de IA, validando fuentes y resguardando la privacidad, para apoyar decisiones laborales. | E13: Herramientas de IA para investigar | F13: Utilizar herramientas de IA para investigar (buscadores con citas, asistentes sobre fuentes propias) y levantar información sobre un problema de su sector. | G13: Aplicar | H13: Tipos de herramientas de investigación con IA; búsqueda con citas; trabajo sobre documentos propios. | I13: Plantear preguntas de investigación y levantar información con al menos dos herramientas distintas. | J13: Curiosidad y autonomía en la búsqueda. | K13: Práctica guiada con herramientas | L13: Rise M3-T1 · Herramientas de IA para investigar | M13: 18 | N13: =M13*'Parámetros'!$C$5 -> 135 | O13: 8 ítems: elegir herramienta según necesidad, formular buenas preguntas | P13: =COUNTIFS(Recursos!$F$5:$F$200,"*"&A13&"*",Recursos!$D$5:$D$200,"Rise") -> 1 | Q13: =COUNTIFS(Recursos!$F$5:$F$200,"*"&A13&"*",Recursos!$D$5:$D$200,"Quiz formativo") -> 1 | R13: =COUNTIFS(Recursos!$F$5:$F$200,"*"&A13&"*",Recursos!$D$5:$D$200,"Caso de aplicación")+COUNTIFS(Recursos!$F$5:$F$200,"*"&A13&"*",Recursos!$D$5:$D$200,"Hito proyecto") -> 1 | S13: =COUNTIFS(Recursos!$F$5:$F$200,"*"&A13&"*",Recursos!$D$5:$D$200,"Evaluación sumativa") -> 1 | T13: =IF(AND(P13>=1,Q13>=1,R13>=1,S13>=1),"OK","Revisar") -> OK
A14: M3-AE2 | B14: 3 | C14: Investigación y análisis de información | D14: Acelerar la investigación y el análisis de información con herramientas de IA, validando fuentes y resguardando la privacidad, para apoyar decisiones laborales. | E14: Recopilar, validar y sintetizar | F14: Contrastar y sintetizar información de múltiples fuentes aplicando criterios de confiabilidad. | G14: Analizar | H14: Criterios de confiabilidad (autoría, fecha, respaldo); triangulación; técnicas de síntesis. | I14: Contrastar hallazgos entre fuentes, descartar los no respaldados y sintetizar lo verificado. | J14: Honestidad intelectual; respeto por la autoría. | K14: Análisis de fuentes con casos reales | L14: Rise M3-T2 · Recopilar, validar y sintetizar | M14: 18 | N14: =M14*'Parámetros'!$C$5 -> 135 | O14: 8 ítems: evaluar confiabilidad de fuentes, identificar contradicciones | P14: =COUNTIFS(Recursos!$F$5:$F$200,"*"&A14&"*",Recursos!$D$5:$D$200,"Rise") -> 1 | Q14: =COUNTIFS(Recursos!$F$5:$F$200,"*"&A14&"*",Recursos!$D$5:$D$200,"Quiz formativo") -> 1 | R14: =COUNTIFS(Recursos!$F$5:$F$200,"*"&A14&"*",Recursos!$D$5:$D$200,"Caso de aplicación")+COUNTIFS(Recursos!$F$5:$F$200,"*"&A14&"*",Recursos!$D$5:$D$200,"Hito proyecto") -> 1 | S14: =COUNTIFS(Recursos!$F$5:$F$200,"*"&A14&"*",Recursos!$D$5:$D$200,"Evaluación sumativa") -> 1 | T14: =IF(AND(P14>=1,Q14>=1,R14>=1,S14>=1),"OK","Revisar") -> OK
A15: M3-AE3 | B15: 3 | C15: Investigación y análisis de información | D15: Acelerar la investigación y el análisis de información con herramientas de IA, validando fuentes y resguardando la privacidad, para apoyar decisiones laborales. | E15: Organizar y presentar información | F15: Organizar y presentar hallazgos en un informe breve con fuentes citadas y mensajes clave. | G15: Aplicar | H15: Estructura de un informe breve; citación de fuentes; visualización simple de datos. | I15: Elaborar un informe breve de 1–2 páginas con hallazgos, fuentes y recomendaciones. | J15: Claridad y orden en la comunicación de resultados. | K15: Taller práctico (producto) | L15: Rise M3-T3 · Organizar y presentar información | M15: 17 | N15: =M15*'Parámetros'!$C$5 -> 127.5 | O15: 8 ítems: ordenar estructura del informe, corregir citas incompletas | P15: =COUNTIFS(Recursos!$F$5:$F$200,"*"&A15&"*",Recursos!$D$5:$D$200,"Rise") -> 1 | Q15: =COUNTIFS(Recursos!$F$5:$F$200,"*"&A15&"*",Recursos!$D$5:$D$200,"Quiz formativo") -> 1 | R15: =COUNTIFS(Recursos!$F$5:$F$200,"*"&A15&"*",Recursos!$D$5:$D$200,"Caso de aplicación")+COUNTIFS(Recursos!$F$5:$F$200,"*"&A15&"*",Recursos!$D$5:$D$200,"Hito proyecto") -> 1 | S15: =COUNTIFS(Recursos!$F$5:$F$200,"*"&A15&"*",Recursos!$D$5:$D$200,"Evaluación sumativa") -> 1 | T15: =IF(AND(P15>=1,Q15>=1,R15>=1,S15>=1),"OK","Revisar") -> OK
A16: M3-AE4 | B16: 3 | C16: Investigación y análisis de información | D16: Acelerar la investigación y el análisis de información con herramientas de IA, validando fuentes y resguardando la privacidad, para apoyar decisiones laborales. | E16: Análisis crítico y privacidad | F16: Evaluar críticamente los resultados de la IA y los riesgos de privacidad al usar información laboral, proponiendo prácticas de uso seguro. | G16: Evaluar | H16: Sesgos, trazabilidad y límites; datos personales y confidenciales; Ley 19.628 y políticas internas; buenas prácticas de uso seguro. | I16: Clasificar información según sensibilidad y decidir qué puede ingresar a una herramienta de IA. | J16: Responsabilidad y ética en el tratamiento de la información; confidencialidad. | K16: Aprendizaje basado en casos reales (incidentes documentados) | L16: Rise M3-T4 · Análisis crítico y privacidad | M16: 18 | N16: =M16*'Parámetros'!$C$5 -> 135 | O16: 8 ítems: clasificar datos por sensibilidad, decidir ante escenarios | P16: =COUNTIFS(Recursos!$F$5:$F$200,"*"&A16&"*",Recursos!$D$5:$D$200,"Rise") -> 1 | Q16: =COUNTIFS(Recursos!$F$5:$F$200,"*"&A16&"*",Recursos!$D$5:$D$200,"Quiz formativo") -> 1 | R16: =COUNTIFS(Recursos!$F$5:$F$200,"*"&A16&"*",Recursos!$D$5:$D$200,"Caso de aplicación")+COUNTIFS(Recursos!$F$5:$F$200,"*"&A16&"*",Recursos!$D$5:$D$200,"Hito proyecto") -> 2 | S16: =COUNTIFS(Recursos!$F$5:$F$200,"*"&A16&"*",Recursos!$D$5:$D$200,"Evaluación sumativa") -> 1 | T16: =IF(AND(P16>=1,Q16>=1,R16>=1,S16>=1),"OK","Revisar") -> OK
... A26: M6-AE3 | B26: 6 | C26: Taller de IA generativa para entornos laborales | D26: Aplicar la IA generativa en un proyecto basado en un desafío laboral real, midiendo resultados y comunicándolos, integrando lo aprendido en los módulos anteriores. | E26: Resultados y aprendizajes | F26: Evaluar los resultados del proyecto y comunicarlos mediante un pitch y un portafolio, proponiendo mejoras. | G26: Evaluar | H26: Medición de resultados; storytelling de resultados; estructura de pitch y portafolio. | I26: Medir resultados contra la línea base, elaborar el pitch y el portafolio, y proponer mejoras. | J26: Autocrítica constructiva; comunicación honesta de resultados, incluidos los límites. | K26: Proyecto aplicado con retroalimentación del tutor | L26: Rise M6-T3 · Resultados y aprendizajes | M26: 9 | N26: =M26*'Parámetros'!$C$5 -> 67.5 | O26: 8 ítems: interpretar resultados, ordenar estructura de un pitch | P26: =COUNTIFS(Recursos!$F$5:$F$200,"*"&A26&"*",Recursos!$D$5:$D$200,"Rise") -> 1 | Q26: =COUNTIFS(Recursos!$F$5:$F$200,"*"&A26&"*",Recursos!$D$5:$D$200,"Quiz formativo") -> 1 | R26: =COUNTIFS(Recursos!$F$5:$F$200,"*"&A26&"*",Recursos!$D$5:$D$200,"Caso de aplicación")+COUNTIFS(Recursos!$F$5:$F$200,"*"&A26&"*",Recursos!$D$5:$D$200,"Hito proyecto") -> 2 | S26: =COUNTIFS(Recursos!$F$5:$F$200,"*"&A26&"*",Recursos!$D$5:$D$200,"Evaluación sumativa") -> 1 | T26: =IF(AND(P26>=1,Q26>=1,R26>=1,S26>=1),"OK","Revisar") -> OK

Sheet Matriz coherencia
A1: Matriz de coherencia curricular
A2: RE 2.484 IV.2.2 b) y IV.3 a), b), c), f): competencia, AE, contenidos, técnicas, actividades, duración y evaluación deben ser coherentes entre sí.
A4: ID AE | B4: Módulo | C4: Competencia del módulo | D4: Aprendizaje esperado | E4: Bloom | F4: Contenidos (saber hacer) | G4: Técnica metodológica | H4: Actividades que lo trabajan | I4: Criterios de evaluación | J4: Instrumentos | K4: Min directos AE (Rise + quiz) | L4: Cobertura
A5: M1-AE1 | B5: 1 | C5: =Estructura!D5 -> Interactuar con modelos de IA generativa mediante prompts efectivos y validación de resultados, para apoyar tareas de oficina de forma verificada. | D5: =Estructura!F5 -> Explicar el funcionamiento general, los tipos y los límites de la IA generativa, ejemplificando sus usos en tareas laborales cotidianas. | E5: Comprender | F5: =Estructura!J5 -> Curiosidad crítica; apertura a un uso responsable de la tecnología. | G5: Exposición interactiva en Rise + ejemplos guiados | H5: Rise: Rise M1-T1 · Fundamentos de IA generativa; Foro M1; P1 (Hito proyecto) | I5: C1 Describe correctamente el funcionamiento y los tipos de IA generativa. C2 Ejemplifica al menos 3 usos y 2 límites en tareas laborales. | J5: Quiz formativo M1-AE1; Evaluación sumativa M1; Rúbrica P1; Evaluación final integradora | K5: =Estructura!N5+'Parámetros'!$C$6 -> 135 | L5: =Estructura!T5 -> OK
A6: M1-AE2 | B6: 1 | C6: =Estructura!D6 -> Interactuar con modelos de IA generativa mediante prompts efectivos y validación de resultados, para apoyar tareas de oficina de forma verificada. | D6: =Estructura!F6 -> Formular prompts efectivos con rol, contexto, tarea y formato para obtener respuestas útiles en tareas laborales simples. | E6: Aplicar | F6: =Estructura!J6 -> Perseverancia en la iteración; orden y documentación del propio trabajo. | G6: Práctica guiada con ejemplos antes/después + laboratorio de prompts | H6: Rise: Rise M1-T2 · Prompts efectivos; Foro M1; P1 (Hito proyecto); C1 (Caso de aplicación) | I6: C1 Incluye rol, contexto, tarea y formato en el prompt. C2 Obtiene una respuesta útil tras iterar al menos una vez. | J6: Quiz formativo M1-AE2; Evaluación sumativa M1; Rúbrica P1; Análisis de caso C1; Evaluación final integradora | K6: =Estructura!N6+'Parámetros'!$C$6 -> 135 | L6: =Estructura!T6 -> OK
A7: M1-AE3 | B7: 1 | C7: =Estructura!D7 -> Interactuar con modelos de IA generativa mediante prompts efectivos y validación de resultados, para apoyar tareas de oficina de forma verificada. | D7: =Estructura!F7 -> Ajustar parámetros de generación (temperatura, longitud, iteración) para adecuar las respuestas a distintos objetivos de una tarea. | E7: Aplicar | F7: =Estructura!J7 -> Rigor al comparar y registrar resultados. | G7: Experimentación guiada (comparación de salidas) | H7: Rise: Rise M1-T3 · Parámetros de generación; Foro M1; C1 (Caso de aplicación) | I7: C1 Elige un parámetro adecuado al objetivo y lo justifica. C2 Compara salidas de una misma consigna y selecciona la mejor con fundamento. | J7: Quiz formativo M1-AE3; Evaluación sumativa M1; Análisis de caso C1; Evaluación final integradora | K7: =Estructura!N7+'Parámetros'!$C$6 -> 135 | L7: =Estructura!T7 -> OK
A8: M1-AE4 | B8: 1 | C8: =Estructura!D8 -> Interactuar con modelos de IA generativa mediante prompts efectivos y validación de resultados, para apoyar tareas de oficina de forma verificada. | D8: =Estructura!F8 -> Validar resultados generados por IA, contrastándolos con fuentes confiables, para detectar alucinaciones, errores y sesgos. | E8: Evaluar | F8: =Estructura!J8 -> Responsabilidad profesional sobre lo que se firma o comparte; honestidad intelectual. | G8: Aprendizaje basado en casos reales (errores documentados) | H8: Rise: Rise M1-T4 · Validación de resultados; Foro M1; C2 (Caso de aplicación) | I8: C1 Identifica errores o sesgos en una respuesta generada. C2 Contrasta con al menos 2 fuentes confiables y corrige o descarta lo no verificable. | J8: Quiz formativo M1-AE4; Evaluación sumativa M1; Análisis de caso C2; Evaluación final integradora | K8: =Estructura!N8+'Parámetros'!$C$6 -> 142.5 | L8: =Estructura!T8 -> OK
A9: M2-AE1 | B9: 2 | C9: =Estructura!D9 -> Optimizar la elaboración de documentos, presentaciones y planillas de cálculo con IA generativa, cuidando tono, audiencia y exactitud, en contextos laborales. | D9: =Estructura!F9 -> Redactar correos, minutas e informes con apoyo de IA, ajustando tono, registro y audiencia. | E9: Aplicar | F9: =Estructura!J9 -> Cortesía y claridad en la comunicación profesional; responsabilidad sobre el mensaje. | G9: Práctica guiada con casos de comunicación laboral | H9: Rise: Rise M2-T1 · Redacción y comunicación con IA; Foro M2; P2 (Hito proyecto); C1 (Caso de aplicación) | I9: C1 Ajusta tono y registro a la audiencia indicada. C2 Entrega un texto claro y sin errores relevantes. | J9: Quiz formativo M2-AE1; Evaluación sumativa M2; Rúbrica P2; Análisis de caso C1; Evaluación final integradora | K9: =Estructura!N9+'Parámetros'!$C$6 -> 150 | L9: =Estructura!T9 -> OK
A10: M2-AE2 | B10: 2 | C10: =Estructura!D10 -> Optimizar la elaboración de documentos, presentaciones y planillas de cálculo con IA generativa, cuidando tono, audiencia y exactitud, en contextos laborales. | D10: =Estructura!F10 -> Aplicar técnicas de prompting avanzado (ejemplos, restricciones, encadenamiento) para mejorar la calidad y consistencia de textos profesionales. | E10: Aplicar | F10: =Estructura!J10 -> Orden metodológico; mejora continua del propio proceso. | G10: Laboratorio de prompts con comparación de versiones | H10: Rise: Rise M2-T2 · Prompting avanzado para textos; Foro M2; C1 (Caso de aplicación) | I10: C1 Aplica al menos dos técnicas (ejemplos, restricciones, encadenamiento). C2 Obtiene textos consistentes entre versiones. | J10: Quiz formativo M2-AE2; Evaluación sumativa M2; Análisis de caso C1; Evaluación final integradora | K10: =Estructura!N10+'Parámetros'!$C$6 -> 150 | L10: =Estructura!T10 -> OK
A11: M2-AE3 | B11: 2 | C11: =Estructura!D11 -> Optimizar la elaboración de documentos, presentaciones y planillas de cálculo con IA generativa, cuidando tono, audiencia y exactitud, en contextos laborales. | D11: =Estructura!F11 -> Estructurar presentaciones de 6 láminas con apoyo de IA a partir de un mensaje clave y una audiencia definida. | E11: Aplicar | F11: =Estructura!J11 -> Sentido de síntesis; cuidado de la imagen profesional. | G11: Taller práctico guiado (producto) | H11: Rise: Rise M2-T3 · Presentaciones con IA; Foro M2; P2 (Hito proyecto); C2 (Caso de aplicación) | I11: C1 Estructura 6 láminas con un mensaje clave coherente. C2 Depura el contenido generado (sobrecarga, errores). | J11: Quiz formativo M2-AE3; Evaluación sumativa M2; Rúbrica P2; Análisis de caso C2; Evaluación final integradora | K11: =Estructura!N11+'Parámetros'!$C$6 -> 142.5 | L11: =Estructura!T11 -> OK
A12: M2-AE4 | B12: 2 | C12: =Estructura!D12 -> Optimizar la elaboración de documentos, presentaciones y planillas de cálculo con IA generativa, cuidando tono, audiencia y exactitud, en contextos laborales. | D12: =Estructura!F12 -> Resolver análisis en planillas de cálculo con fórmulas generadas por IA, verificando su exactitud. | E12: Evaluar | F12: =Estructura!J12 -> Rigor numérico; desconfianza metódica ante resultados no comprobados. | G12: Resolución de problemas con datos de práctica | H12: Rise: Rise M2-T4 · Planillas de cálculo con IA; Foro M2; C2 (Caso de aplicación) | I12: C1 Genera una fórmula correcta para el problema planteado. C2 Comprueba el resultado con datos de prueba y corrige errores. | J12: Quiz formativo M2-AE4; Evaluación sumativa M2; Análisis de caso C2; Evaluación final integradora | K12: =Estructura!N12+'Parámetros'!$C$6 -> 150 | L12: =Estructura!T12 -> OK
A13: M3-AE1 | B13: 3 | C13: =Estructura!D13 -> Acelerar la investigación y el análisis de información con herramientas de IA, validando fuentes y resguardando la privacidad, para apoyar decisiones laborales. | D13: =Estructura!F13 -> Utilizar herramientas de IA para investigar (buscadores con citas, asistentes sobre fuentes propias) y levantar información sobre un problema de su sector. | E13: Aplicar | F13: =Estructura!J13 -> Curiosidad y autonomía en la búsqueda. | G13: Práctica guiada con herramientas | H13: Rise: Rise M3-T1 · Herramientas de IA para investigar; Foro M3; P3 (Hito proyecto) | I13: C1 Formula preguntas de investigación específicas. C2 Usa al menos 2 herramientas y registra las fuentes con su cita. | J13: Quiz formativo M3-AE1; Evaluación sumativa M3; Rúbrica P3; Evaluación final integradora | K13: =Estructura!N13+'Parámetros'!$C$6 -> 150 | L13: =Estructura!T13 -> OK
A14: M3-AE2 | B14: 3 | C14: =Estructura!D14 -> Acelerar la investigación y el análisis de información con herramientas de IA, validando fuentes y resguardando la privacidad, para apoyar decisiones laborales. | D14: =Estructura!F14 -> Contrastar y sintetizar información de múltiples fuentes aplicando criterios de confiabilidad. | E14: Analizar | F14: =Estructura!J14 -> Honestidad intelectual; respeto por la autoría. | G14: Análisis de fuentes con casos reales | H14: Rise: Rise M3-T2 · Recopilar, validar y sintetizar; Foro M3; C1 (Caso de aplicación) | I14: C1 Aplica criterios de confiabilidad (autoría, fecha, respaldo). C2 Sintetiza hallazgos contrastados sin afirmaciones sin respaldo. | J14: Quiz formativo M3-AE2; Evaluación sumativa M3; Análisis de caso C1; Evaluación final integradora | K14: =Estructura!N14+'Parámetros'!$C$6 -> 150 | L14: =Estructura!T14 -> OK
A15: M3-AE3 | B15: 3 | C15: =Estructura!D15 -> Acelerar la investigación y el análisis de información con herramientas de IA, validando fuentes y resguardando la privacidad, para apoyar decisiones laborales. | D15: =Estructura!F15 -> Organizar y presentar hallazgos en un informe breve con fuentes citadas y mensajes clave. | E15: Aplicar | F15: =Estructura!J15 -> Claridad y orden en la comunicación de resultados. | G15: Taller práctico (producto) | H15: Rise: Rise M3-T3 · Organizar y presentar información; Foro M3; P3 (Hito proyecto) | I15: C1 Organiza el informe con una estructura definida. C2 Cita todas las fuentes y formula recomendaciones. | J15: Quiz formativo M3-AE3; Evaluación sumativa M3; Rúbrica P3; Evaluación final integradora | K15: =Estructura!N15+'Parámetros'!$C$6 -> 142.5 | L15: =Estructura!T15 -> OK
A16: M3-AE4 | B16: 3 | C16: =Estructura!D16 -> Acelerar la investigación y el análisis de información con herramientas de IA, validando fuentes y resguardando la privacidad, para apoyar decisiones laborales. | D16: =Estructura!F16 -> Evaluar críticamente los resultados de la IA y los riesgos de privacidad al usar información laboral, proponiendo prácticas de uso seguro. | E16: Evaluar | F16: =Estructura!J16 -> Responsabilidad y ética en el tratamiento de la información; confidencialidad. | G16: Aprendizaje basado en casos reales (incidentes documentados) | H16: Rise: Rise M3-T4 · Análisis crítico y privacidad; Foro M3; C1 (Caso de aplicación); C2 (Caso de aplicación) | I16: C1 Clasifica la información según su sensibilidad. C2 Decide con fundamento qué puede ingresar a una herramienta de IA y propone una práctica segura. | J16: Quiz formativo M3-AE4; Evaluación sumativa M3; Análisis de caso C1; Análisis de caso C2; Evaluación final integradora | K16: =Estructura!N16+'Parámetros'!$C$6 -> 150 | L16: =Estructura!T16 -> OK
... A26: M6-AE3 | B26: 6 | C26: =Estructura!D26 -> Aplicar la IA generativa en un proyecto basado en un desafío laboral real, midiendo resultados y comunicándolos, integrando lo aprendido en los módulos anteriores. | D26: =Estructura!F26 -> Evaluar los resultados del proyecto y comunicarlos mediante un pitch y un portafolio, proponiendo mejoras. | E26: Evaluar | F26: =Estructura!J26 -> Autocrítica constructiva; comunicación honesta de resultados, incluidos los límites. | G26: Proyecto aplicado con retroalimentación del tutor | H26: Rise: Rise M6-T3 · Resultados y aprendizajes; Foro M6; P6c (Hito proyecto); P6d (Hito proyecto) | I26: C1 Compara los resultados con la línea base. C2 Comunica resultados y límites con claridad en un pitch de 3 minutos. | J26: Quiz formativo M6-AE3; Evaluación sumativa M6; Rúbrica P6c; Rúbrica P6d; Evaluación final integradora | K26: =Estructura!N26+'Parámetros'!$C$6 -> 82.5 | L26: =Estructura!T26 -> OK

Sheet Recursos
A1: Recursos por módulo (en orden de aprendizaje)
A2: Cada fila es un recurso producible. Duración en minutos calculada con los parámetros. Estado y responsable se editan.
A4: ID | B4: Módulo | C4: Orden | D4: Tipo | E4: Recurso / título | F4: AE que trabaja | G4: Duración (min) | H4: Cuenta en horas | I4: Interacción facilitador/tutor | J4: Formato / herramienta | K4: Responsable | L4: Archivo o guion | M4: Estado
A5: R001 | B5: 1 | C5: =COUNTIFS($B$5:B5,B5) -> 1 | D5: Inducción/Diagnóstica | E5: Inducción tecnológica-metodológica (video) + Guía del participante + Evaluación diagnóstica | F5: — | G5: ='Parámetros'!$C$11 -> 45 | H5: Sí | I5: No | J5: Video + PDF + cuestionario | K5: Diseño instruccional | M5: Pendiente
A6: R002 | B6: 1 | C6: =COUNTIFS($B$5:B6,B6) -> 2 | D6: Video | E6: Video de bienvenida M1 (3 min): qué aprenderás, cómo se evalúa, hito del proyecto | F6: — | G6: ='Parámetros'!$C$8 -> 3 | H6: Sí | I6: No | J6: Video con avatar/locución | K6: Diseño instruccional | M6: Pendiente
A7: R003 | B7: 1 | C7: =COUNTIFS($B$5:B7,B7) -> 3 | D7: Rise | E7: Rise M1-T1 · Fundamentos de IA generativa | F7: M1-AE1 | G7: =Estructura!N5 -> 120 | H7: Sí | I7: No | J7: Rise (pantallas) | K7: Diseño instruccional | M7: Pendiente
A8: R004 | B8: 1 | C8: =COUNTIFS($B$5:B8,B8) -> 4 | D8: Quiz formativo | E8: Quiz formativo M1-AE1 · Fundamentos de IA generativa | F8: M1-AE1 | G8: ='Parámetros'!$C$6 -> 15 | H8: Sí | I8: No | J8: Quiz automatizado con retroalimentación + acción remedial | K8: Diseño instruccional | M8: Pendiente
A9: R005 | B9: 1 | C9: =COUNTIFS($B$5:B9,B9) -> 5 | D9: Rise | E9: Rise M1-T2 · Prompts efectivos | F9: M1-AE2 | G9: =Estructura!N6 -> 120 | H9: Sí | I9: No | J9: Rise (pantallas) | K9: Diseño instruccional | M9: Pendiente
A10: R006 | B10: 1 | C10: =COUNTIFS($B$5:B10,B10) -> 6 | D10: Quiz formativo | E10: Quiz formativo M1-AE2 · Prompts efectivos | F10: M1-AE2 | G10: ='Parámetros'!$C$6 -> 15 | H10: Sí | I10: No | J10: Quiz automatizado con retroalimentación + acción remedial | K10: Diseño instruccional | M10: Pendiente
A11: R007 | B11: 1 | C11: =COUNTIFS($B$5:B11,B11) -> 7 | D11: Rise | E11: Rise M1-T3 · Parámetros de generación | F11: M1-AE3 | G11: =Estructura!N7 -> 120 | H11: Sí | I11: No | J11: Rise (pantallas) | K11: Diseño instruccional | M11: Pendiente
A12: R008 | B12: 1 | C12: =COUNTIFS($B$5:B12,B12) -> 8 | D12: Quiz formativo | E12: Quiz formativo M1-AE3 · Parámetros de generación | F12: M1-AE3 | G12: ='Parámetros'!$C$6 -> 15 | H12: Sí | I12: No | J12: Quiz automatizado con retroalimentación + acción remedial | K12: Diseño instruccional | M12: Pendiente
A13: R009 | B13: 1 | C13: =COUNTIFS($B$5:B13,B13) -> 9 | D13: Rise | E13: Rise M1-T4 · Validación de resultados | F13: M1-AE4 | G13: =Estructura!N8 -> 127.5 | H13: Sí | I13: No | J13: Rise (pantallas) | K13: Diseño instruccional | M13: Pendiente
A14: R010 | B14: 1 | C14: =COUNTIFS($B$5:B14,B14) -> 10 | D14: Quiz formativo | E14: Quiz formativo M1-AE4 · Validación de resultados | F14: M1-AE4 | G14: ='Parámetros'!$C$6 -> 15 | H14: Sí | I14: No | J14: Quiz automatizado con retroalimentación + acción remedial | K14: Diseño instruccional | M14: Pendiente
A15: R011 | B15: 1 | C15: =COUNTIFS($B$5:B15,B15) -> 11 | D15: Hito proyecto | E15: Proyecto aplicado · Hito 1: problema u oportunidad real + biblioteca de prompts v1 | F15: M1-AE1; M1-AE2 | G15: ='Parámetros'!$C$10 -> 90 | H15: Sí | I15: Sí | J15: Rise + actividad (caso) / entrega con rúbrica (hito) | K15: Diseño instruccional | M15: Pendiente
A16: R012 | B16: 1 | C16: =COUNTIFS($B$5:B16,B16) -> 12 | D16: Caso de aplicación | E16: Caso M1-C1 · Asistente de IA para asesores financieros (Morgan Stanley) | F16: M1-AE2; M1-AE3 | G16: ='Parámetros'!$C$10 -> 90 | H16: Sí | I16: No | J16: Rise + actividad (caso) / entrega con rúbrica (hito) | K16: Diseño instruccional | M16: Pendiente
A17: R013 | B17: 1 | C17: =COUNTIFS($B$5:B17,B17) -> 13 | D17: Caso de aplicación | E17: Caso M1-C2 · Cuando la IA inventa: abogados y jurisprudencia inexistente (Mata v. Avianca, 2023) y chatbot de Air Canada (2024) | F17: M1-AE4 | G17: ='Parámetros'!$C$10 -> 90 | H17: Sí | I17: No | J17: Rise + actividad (caso) / entrega con rúbrica (hito) | K17: Diseño instruccional | M17: Pendiente
A18: R014 | B18: 1 | C18: =COUNTIFS($B$5:B18,B18) -> 14 | D18: Foro | E18: Foro M1: discusión guiada del módulo (tutor responde en <24 h hábiles) | F18: M1-AE1; M1-AE2; M1-AE3; M1-AE4 | G18: ='Parámetros'!$C$7 -> 30 | H18: Sí | I18: Sí | J18: Foro Moodle | K18: Diseño instruccional | M18: Pendiente
A19: R015 | B19: 1 | C19: =COUNTIFS($B$5:B19,B19) -> 15 | D19: Video | E19: Video de resumen M1 (3 min): ideas clave y conexión con el siguiente módulo | F19: — | G19: ='Parámetros'!$C$9 -> 3 | H19: Sí | I19: No | J19: Video con avatar/locución | K19: Diseño instruccional | M19: Pendiente
A20: R016 | B20: 1 | C20: =COUNTIFS($B$5:B20,B20) -> 16 | D20: Resumen y glosario | E20: Resumen y glosario del módulo M1 (página; lectura 1,5 min) | F20: — | G20: 1.5 | H20: Sí | I20: No | J20: Página Moodle | K20: Diseño instruccional | M20: Pendiente
A21: R017 | B21: 1 | C21: =COUNTIFS($B$5:B21,B21) -> 17 | D21: Complemento | E21: Infografía M1: Anatomía de un prompt efectivo (rol · contexto · tarea · formato) | F21: — | G21: 0 | H21: No | I21: No | J21: Infografía (imagen) | K21: Diseño instruccional | M21: Pendiente
A22: R018 | B22: 1 | C22: =COUNTIFS($B$5:B22,B22) -> 18 | D22: Evaluación sumativa | E22: Evaluación sumativa M1 | F22: M1-AE1; M1-AE2; M1-AE3; M1-AE4 | G22: 60 | H22: Sí | I22: No | J22: Cuestionario Moodle con retroalimentación automática | K22: Diseño instruccional | M22: Pendiente
A23: R019 | B23: 2 | C23: =COUNTIFS($B$5:B23,B23) -> 1 | D23: Video | E23: Video de bienvenida M2 (3 min): qué aprenderás, cómo se evalúa, hito del proyecto | F23: — | G23: ='Parámetros'!$C$8 -> 3 | H23: Sí | I23: No | J23: Video con avatar/locución | K23: Diseño instruccional | M23: Pendiente
A24: R020 | B24: 2 | C24: =COUNTIFS($B$5:B24,B24) -> 2 | D24: Rise | E24: Rise M2-T1 · Redacción y comunicación con IA | F24: M2-AE1 | G24: =Estructura!N9 -> 135 | H24: Sí | I24: No | J24: Rise (pantallas) | K24: Diseño instruccional | M24: Pendiente
A25: R021 | B25: 2 | C25: =COUNTIFS($B$5:B25,B25) -> 3 | D25: Quiz formativo | E25: Quiz formativo M2-AE1 · Redacción y comunicación con IA | F25: M2-AE1 | G25: ='Parámetros'!$C$6 -> 15 | H25: Sí | I25: No | J25: Quiz automatizado con retroalimentación + acción remedial | K25: Diseño instruccional | M25: Pendiente
A26: R022 | B26: 2 | C26: =COUNTIFS($B$5:B26,B26) -> 4 | D26: Rise | E26: Rise M2-T2 · Prompting avanzado para textos | F26: M2-AE2 | G26: =Estructura!N10 -> 135 | H26: Sí | I26: No | J26: Rise (pantallas) | K26: Diseño instruccional | M26: Pendiente
A27: R023 | B27: 2 | C27: =COUNTIFS($B$5:B27,B27) -> 5 | D27: Quiz formativo | E27: Quiz formativo M2-AE2 · Prompting avanzado para textos | F27: M2-AE2 | G27: ='Parámetros'!$C$6 -> 15 | H27: Sí | I27: No | J27: Quiz automatizado con retroalimentación + acción remedial | K27: Diseño instruccional | M27: Pendiente
A28: R024 | B28: 2 | C28: =COUNTIFS($B$5:B28,B28) -> 6 | D28: Rise | E28: Rise M2-T3 · Presentaciones con IA | F28: M2-AE3 | G28: =Estructura!N11 -> 127.5 | H28: Sí | I28: No | J28: Rise (pantallas) | K28: Diseño instruccional | M28: Pendiente
A29: R025 | B29: 2 | C29: =COUNTIFS($B$5:B29,B29) -> 7 | D29: Quiz formativo | E29: Quiz formativo M2-AE3 · Presentaciones con IA | F29: M2-AE3 | G29: ='Parámetros'!$C$6 -> 15 | H29: Sí | I29: No | J29: Quiz automatizado con retroalimentación + acción remedial | K29: Diseño instruccional | M29: Pendiente
A30: R026 | B30: 2 | C30: =COUNTIFS($B$5:B30,B30) -> 8 | D30: Rise | E30: Rise M2-T4 · Planillas de cálculo con IA | F30: M2-AE4 | G30: =Estructura!N12 -> 135 | H30: Sí | I30: No | J30: Rise (pantallas) | K30: Diseño instruccional | M30: Pendiente
A31: R027 | B31: 2 | C31: =COUNTIFS($B$5:B31,B31) -> 9 | D31: Quiz formativo | E31: Quiz formativo M2-AE4 · Planillas de cálculo con IA | F31: M2-AE4 | G31: ='Parámetros'!$C$6 -> 15 | H31: Sí | I31: No | J31: Quiz automatizado con retroalimentación + acción remedial | K31: Diseño instruccional | M31: Pendiente
A32: R028 | B32: 2 | C32: =COUNTIFS($B$5:B32,B32) -> 10 | D32: Hito proyecto | E32: Proyecto aplicado · Hito 2: brief del proyecto + presentación de 6 láminas | F32: M2-AE1; M2-AE3 | G32: ='Parámetros'!$C$10 -> 90 | H32: Sí | I32: Sí | J32: Rise + actividad (caso) / entrega con rúbrica (hito) | K32: Diseño instruccional | M32: Pendiente
A33: R029 | B33: 2 | C33: =COUNTIFS($B$5:B33,B33) -> 11 | D33: Caso de aplicación | E33: Caso M2-C1 · Comunicación con clientes redactada con apoyo de IA (Octopus Energy) | F33: M2-AE1; M2-AE2 | G33: ='Parámetros'!$C$10 -> 90 | H33: Sí | I33: No | J33: Rise + actividad (caso) / entrega con rúbrica (hito) | K33: Diseño instruccional | M33: Pendiente
A34: R030 | B34: 2 | C34: =COUNTIFS($B$5:B34,B34) -> 12 | D34: Caso de aplicación | E34: Caso M2-C2 · Asistente de IA en herramientas de oficina para equipos (Vodafone y Microsoft 365 Copilot) | F34: M2-AE3; M2-AE4 | G34: ='Parámetros'!$C$10 -> 90 | H34: Sí | I34: No | J34: Rise + actividad (caso) / entrega con rúbrica (hito) | K34: Diseño instruccional | M34: Pendiente
A35: R031 | B35: 2 | C35: =COUNTIFS($B$5:B35,B35) -> 13 | D35: Foro | E35: Foro M2: discusión guiada del módulo (tutor responde en <24 h hábiles) | F35: M2-AE1; M2-AE2; M2-AE3; M2-AE4 | G35: ='Parámetros'!$C$7 -> 30 | H35: Sí | I35: Sí | J35: Foro Moodle | K35: Diseño instruccional | M35: Pendiente
A36: R032 | B36: 2 | C36: =COUNTIFS($B$5:B36,B36) -> 14 | D36: Video | E36: Video de resumen M2 (3 min): ideas clave y conexión con el siguiente módulo | F36: — | G36: ='Parámetros'!$C$9 -> 3 | H36: Sí | I36: No | J36: Video con avatar/locución | K36: Diseño instruccional | M36: Pendiente
A37: R033 | B37: 2 | C37: =COUNTIFS($B$5:B37,B37) -> 15 | D37: Resumen y glosario | E37: Resumen y glosario del módulo M2 (página; lectura 1,5 min) | F37: — | G37: 1.5 | H37: Sí | I37: No | J37: Página Moodle | K37: Diseño instruccional | M37: Pendiente
A38: R034 | B38: 2 | C38: =COUNTIFS($B$5:B38,B38) -> 16 | D38: Complemento | E38: Infografía M2: Flujo de redacción aumentada (borrador → ajuste → verificación) | F38: — | G38: 0 | H38: No | I38: No | J38: Infografía (imagen) | K38: Diseño instruccional | M38: Pendiente
A39: R035 | B39: 2 | C39: =COUNTIFS($B$5:B39,B39) -> 17 | D39: Evaluación sumativa | E39: Evaluación sumativa M2 | F39: M2-AE1; M2-AE2; M2-AE3; M2-AE4 | G39: 60 | H39: Sí | I39: No | J39: Cuestionario Moodle con retroalimentación automática | K39: Diseño instruccional | M39: Pendiente
A40: R036 | B40: 3 | C40: =COUNTIFS($B$5:B40,B40) -> 1 | D40: Video | E40: Video de bienvenida M3 (3 min): qué aprenderás, cómo se evalúa, hito del proyecto | F40: — | G40: ='Parámetros'!$C$8 -> 3 | H40: Sí | I40: No | J40: Video con avatar/locución | K40: Diseño instruccional | M40: Pendiente
A41: R037 | B41: 3 | C41: =COUNTIFS($B$5:B41,B41) -> 2 | D41: Rise | E41: Rise M3-T1 · Herramientas de IA para investigar | F41: M3-AE1 | G41: =Estructura!N13 -> 135 | H41: Sí | I41: No | J41: Rise (pantallas) | K41: Diseño instruccional | M41: Pendiente
A42: R038 | B42: 3 | C42: =COUNTIFS($B$5:B42,B42) -> 3 | D42: Quiz formativo | E42: Quiz formativo M3-AE1 · Herramientas de IA para investigar | F42: M3-AE1 | G42: ='Parámetros'!$C$6 -> 15 | H42: Sí | I42: No | J42: Quiz automatizado con retroalimentación + acción remedial | K42: Diseño instruccional | M42: Pendiente
A43: R039 | B43: 3 | C43: =COUNTIFS($B$5:B43,B43) -> 4 | D43: Rise | E43: Rise M3-T2 · Recopilar, validar y sintetizar | F43: M3-AE2 | G43: =Estructura!N14 -> 135 | H43: Sí | I43: No | J43: Rise (pantallas) | K43: Diseño instruccional | M43: Pendiente
A44: R040 | B44: 3 | C44: =COUNTIFS($B$5:B44,B44) -> 5 | D44: Quiz formativo | E44: Quiz formativo M3-AE2 · Recopilar, validar y sintetizar | F44: M3-AE2 | G44: ='Parámetros'!$C$6 -> 15 | H44: Sí | I44: No | J44: Quiz automatizado con retroalimentación + acción remedial | K44: Diseño instruccional | M44: Pendiente
A45: R041 | B45: 3 | C45: =COUNTIFS($B$5:B45,B45) -> 6 | D45: Rise | E45: Rise M3-T3 · Organizar y presentar información | F45: M3-AE3 | G45: =Estructura!N15 -> 127.5 | H45: Sí | I45: No | J45: Rise (pantallas) | K45: Diseño instruccional | M45: Pendiente
A46: R042 | B46: 3 | C46: =COUNTIFS($B$5:B46,B46) -> 7 | D46: Quiz formativo | E46: Quiz formativo M3-AE3 · Organizar y presentar información | F46: M3-AE3 | G46: ='Parámetros'!$C$6 -> 15 | H46: Sí | I46: No | J46: Quiz automatizado con retroalimentación + acción remedial | K46: Diseño instruccional | M46: Pendiente
A47: R043 | B47: 3 | C47: =COUNTIFS($B$5:B47,B47) -> 8 | D47: Rise | E47: Rise M3-T4 · Análisis crítico y privacidad | F47: M3-AE4 | G47: =Estructura!N16 -> 135 | H47: Sí | I47: No | J47: Rise (pantallas) | K47: Diseño instruccional | M47: Pendiente
A48: R044 | B48: 3 | C48: =COUNTIFS($B$5:B48,B48) -> 9 | D48: Quiz formativo | E48: Quiz formativo M3-AE4 · Análisis crítico y privacidad | F48: M3-AE4 | G48: ='Parámetros'!$C$6 -> 15 | H48: Sí | I48: No | J48: Quiz automatizado con retroalimentación + acción remedial | K48: Diseño instruccional | M48: Pendiente
A49: R045 | B49: 3 | C49: =COUNTIFS($B$5:B49,B49) -> 10 | D49: Hito proyecto | E49: Proyecto aplicado · Hito 3: investigación validada con fuentes (informe breve) | F49: M3-AE1; M3-AE3 | G49: ='Parámetros'!$C$10 -> 90 | H49: Sí | I49: Sí | J49: Rise + actividad (caso) / entrega con rúbrica (hito) | K49: Diseño instruccional | M49: Pendiente
A50: R046 | B50: 3 | C50: =COUNTIFS($B$5:B50,B50) -> 11 | D50: Caso de aplicación | E50: Caso M3-C1 · Informe con referencias inexistentes generadas por IA (Deloitte Australia, 2025) | F50: M3-AE2; M3-AE4 | G50: ='Parámetros'!$C$10 -> 90 | H50: Sí | I50: No | J50: Rise + actividad (caso) / entrega con rúbrica (hito) | K50: Diseño instruccional | M50: Pendiente
A51: R047 | B51: 3 | C51: =COUNTIFS($B$5:B51,B51) -> 12 | D51: Caso de aplicación | E51: Caso M3-C2 · Información confidencial ingresada a una herramienta de IA (Samsung, 2023) | F51: M3-AE4 | G51: ='Parámetros'!$C$10 -> 90 | H51: Sí | I51: No | J51: Rise + actividad (caso) / entrega con rúbrica (hito) | K51: Diseño instruccional | M51: Pendiente
A52: R048 | B52: 3 | C52: =COUNTIFS($B$5:B52,B52) -> 13 | D52: Foro | E52: Foro M3: discusión guiada del módulo (tutor responde en <24 h hábiles) | F52: M3-AE1; M3-AE2; M3-AE3; M3-AE4 | G52: ='Parámetros'!$C$7 -> 30 | H52: Sí | I52: Sí | J52: Foro Moodle | K52: Diseño instruccional | M52: Pendiente
A53: R049 | B53: 3 | C53: =COUNTIFS($B$5:B53,B53) -> 14 | D53: Video | E53: Video de resumen M3 (3 min): ideas clave y conexión con el siguiente módulo | F53: — | G53: ='Parámetros'!$C$9 -> 3 | H53: Sí | I53: No | J53: Video con avatar/locución | K53: Diseño instruccional | M53: Pendiente
A54: R050 | B54: 3 | C54: =COUNTIFS($B$5:B54,B54) -> 15 | D54: Resumen y glosario | E54: Resumen y glosario del módulo M3 (página; lectura 1,5 min) | F54: — | G54: 1.5 | H54: Sí | I54: No | J54: Página Moodle | K54: Diseño instruccional | M54: Pendiente
A55: R051 | B55: 3 | C55: =COUNTIFS($B$5:B55,B55) -> 16 | D55: Complemento | E55: Infografía M3: Ruta de una investigación verificada (buscar · contrastar · sintetizar · citar) | F55: — | G55: 0 | H55: No | I55: No | J55: Infografía (imagen) | K55: Diseño instruccional | M55: Pendiente
A56: R052 | B56: 3 | C56: =COUNTIFS($B$5:B56,B56) -> 17 | D56: Evaluación sumativa | E56: Evaluación sumativa M3 | F56: M3-AE1; M3-AE2; M3-AE3; M3-AE4 | G56: 60 | H56: Sí | I56: No | J56: Cuestionario Moodle con retroalimentación automática | K56: Diseño instruccional | M56: Pendiente
A57: R053 | B57: 4 | C57: =COUNTIFS($B$5:B57,B57) -> 1 | D57: Video | E57: Video de bienvenida M4 (3 min): qué aprenderás, cómo se evalúa, hito del proyecto | F57: — | G57: ='Parámetros'!$C$8 -> 3 | H57: Sí | I57: No | J57: Video con avatar/locución | K57: Diseño instruccional | M57: Pendiente
A58: R054 | B58: 4 | C58: =COUNTIFS($B$5:B58,B58) -> 2 | D58: Rise | E58: Rise M4-T1 · Ecosistema multimedia con IA | F58: M4-AE1 | G58: =Estructura!N17 -> 112.5 | H58: Sí | I58: No | J58: Rise (pantallas) | K58: Diseño instruccional | M58: Pendiente
A59: R055 | B59: 4 | C59: =COUNTIFS($B$5:B59,B59) -> 3 | D59: Quiz formativo | E59: Quiz formativo M4-AE1 · Ecosistema multimedia con IA | F59: M4-AE1 | G59: ='Parámetros'!$C$6 -> 15 | H59: Sí | I59: No | J59: Quiz automatizado con retroalimentación + acción remedial | K59: Diseño instruccional | M59: Pendiente
A60: R056 | B60: 4 | C60: =COUNTIFS($B$5:B60,B60) -> 4 | D60: Rise | E60: Rise M4-T2 · Imágenes y gráficos | F60: M4-AE2 | G60: =Estructura!N18 -> 112.5 | H60: Sí | I60: No | J60: Rise (pantallas) | K60: Diseño instruccional | M60: Pendiente
A61: R057 | B61: 4 | C61: =COUNTIFS($B$5:B61,B61) -> 5 | D61: Quiz formativo | E61: Quiz formativo M4-AE2 · Imágenes y gráficos | F61: M4-AE2 | G61: ='Parámetros'!$C$6 -> 15 | H61: Sí | I61: No | J61: Quiz automatizado con retroalimentación + acción remedial | K61: Diseño instruccional | M61: Pendiente
A62: R058 | B62: 4 | C62: =COUNTIFS($B$5:B62,B62) -> 6 | D62: Rise | E62: Rise M4-T3 · Audio y música | F62: M4-AE3 | G62: =Estructura!N19 -> 105 | H62: Sí | I62: No | J62: Rise (pantallas) | K62: Diseño instruccional | M62: Pendiente
A63: R059 | B63: 4 | C63: =COUNTIFS($B$5:B63,B63) -> 7 | D63: Quiz formativo | E63: Quiz formativo M4-AE3 · Audio y música | F63: M4-AE3 | G63: ='Parámetros'!$C$6 -> 15 | H63: Sí | I63: No | J63: Quiz automatizado con retroalimentación + acción remedial | K63: Diseño instruccional | M63: Pendiente
A64: R060 | B64: 4 | C64: =COUNTIFS($B$5:B64,B64) -> 8 | D64: Rise | E64: Rise M4-T4 · Clips y video breve | F64: M4-AE4 | G64: =Estructura!N20 -> 112.5 | H64: Sí | I64: No | J64: Rise (pantallas) | K64: Diseño instruccional | M64: Pendiente
A65: R061 | B65: 4 | C65: =COUNTIFS($B$5:B65,B65) -> 9 | D65: Quiz formativo | E65: Quiz formativo M4-AE4 · Clips y video breve | F65: M4-AE4 | G65: ='Parámetros'!$C$6 -> 15 | H65: Sí | I65: No | J65: Quiz automatizado con retroalimentación + acción remedial | K65: Diseño instruccional | M65: Pendiente
A66: R062 | B66: 4 | C66: =COUNTIFS($B$5:B66,B66) -> 10 | D66: Hito proyecto | E66: Proyecto aplicado · Hito 4: pieza multimedia que comunica la solución | F66: M4-AE2; M4-AE4 | G66: ='Parámetros'!$C$10 -> 90 | H66: Sí | I66: Sí | J66: Rise + actividad (caso) / entrega con rúbrica (hito) | K66: Diseño instruccional | M66: Pendiente
A67: R063 | B67: 4 | C67: =COUNTIFS($B$5:B67,B67) -> 11 | D67: Caso de aplicación | E67: Caso M4-C1 · Campañas de marca hechas con IA generativa (Coca-Cola, 2023 y 2024) | F67: M4-AE2; M4-AE4 | G67: ='Parámetros'!$C$10 -> 90 | H67: Sí | I67: No | J67: Rise + actividad (caso) / entrega con rúbrica (hito) | K67: Diseño instruccional | M67: Pendiente
A68: R064 | B68: 4 | C68: =COUNTIFS($B$5:B68,B68) -> 12 | D68: Caso de aplicación | E68: Caso M4-C2 · Voz sintética y consentimiento (disputa Scarlett Johansson – OpenAI, 2024) | F68: M4-AE3 | G68: ='Parámetros'!$C$10 -> 90 | H68: Sí | I68: No | J68: Rise + actividad (caso) / entrega con rúbrica (hito) | K68: Diseño instruccional | M68: Pendiente
A69: R065 | B69: 4 | C69: =COUNTIFS($B$5:B69,B69) -> 13 | D69: Caso de aplicación | E69: Caso M4-C3 · Licencias y datos de entrenamiento (Getty Images v. Stability AI) | F69: M4-AE1 | G69: ='Parámetros'!$C$10 -> 90 | H69: Sí | I69: No | J69: Rise + actividad (caso) / entrega con rúbrica (hito) | K69: Diseño instruccional | M69: Pendiente
A70: R066 | B70: 4 | C70: =COUNTIFS($B$5:B70,B70) -> 14 | D70: Foro | E70: Foro M4: discusión guiada del módulo (tutor responde en <24 h hábiles) | F70: M4-AE1; M4-AE2; M4-AE3; M4-AE4 | G70: ='Parámetros'!$C$7 -> 30 | H70: Sí | I70: Sí | J70: Foro Moodle | K70: Diseño instruccional | M70: Pendiente
A71: R067 | B71: 4 | C71: =COUNTIFS($B$5:B71,B71) -> 15 | D71: Video | E71: Video de resumen M4 (3 min): ideas clave y conexión con el siguiente módulo | F71: — | G71: ='Parámetros'!$C$9 -> 3 | H71: Sí | I71: No | J71: Video con avatar/locución | K71: Diseño instruccional | M71: Pendiente
A72: R068 | B72: 4 | C72: =COUNTIFS($B$5:B72,B72) -> 16 | D72: Resumen y glosario | E72: Resumen y glosario del módulo M4 (página; lectura 1,5 min) | F72: — | G72: 1.5 | H72: Sí | I72: No | J72: Página Moodle | K72: Diseño instruccional | M72: Pendiente
A73: R069 | B73: 4 | C73: =COUNTIFS($B$5:B73,B73) -> 17 | D73: Complemento | E73: Infografía M4: Mapa del ecosistema multimedia con IA y semáforo de licencias | F73: — | G73: 0 | H73: No | I73: No | J73: Infografía (imagen) | K73: Diseño instruccional | M73: Pendiente
A74: R070 | B74: 4 | C74: =COUNTIFS($B$5:B74,B74) -> 18 | D74: Evaluación sumativa | E74: Evaluación sumativa M4 | F74: M4-AE1; M4-AE2; M4-AE3; M4-AE4 | G74: 60 | H74: Sí | I74: No | J74: Cuestionario Moodle con retroalimentación automática | K74: Diseño instruccional | M74: Pendiente
A75: R071 | B75: 5 | C75: =COUNTIFS($B$5:B75,B75) -> 1 | D75: Video | E75: Video de bienvenida M5 (3 min): qué aprenderás, cómo se evalúa, hito del proyecto | F75: — | G75: ='Parámetros'!$C$8 -> 3 | H75: Sí | I75: No | J75: Video con avatar/locución | K75: Diseño instruccional | M75: Pendiente
A76: R072 | B76: 5 | C76: =COUNTIFS($B$5:B76,B76) -> 2 | D76: Rise | E76: Rise M5-T1 · Potencial de automatización | F76: M5-AE1 | G76: =Estructura!N21 -> 112.5 | H76: Sí | I76: No | J76: Rise (pantallas) | K76: Diseño instruccional | M76: Pendiente
A77: R073 | B77: 5 | C77: =COUNTIFS($B$5:B77,B77) -> 3 | D77: Quiz formativo | E77: Quiz formativo M5-AE1 · Potencial de automatización | F77: M5-AE1 | G77: ='Parámetros'!$C$6 -> 15 | H77: Sí | I77: No | J77: Quiz automatizado con retroalimentación + acción remedial | K77: Diseño instruccional | M77: Pendiente
A78: R074 | B78: 5 | C78: =COUNTIFS($B$5:B78,B78) -> 4 | D78: Rise | E78: Rise M5-T2 · Flujos simples con IA | F78: M5-AE2 | G78: =Estructura!N22 -> 105 | H78: Sí | I78: No | J78: Rise (pantallas) | K78: Diseño instruccional | M78: Pendiente
A79: R075 | B79: 5 | C79: =COUNTIFS($B$5:B79,B79) -> 5 | D79: Quiz formativo | E79: Quiz formativo M5-AE2 · Flujos simples con IA | F79: M5-AE2 | G79: ='Parámetros'!$C$6 -> 15 | H79: Sí | I79: No | J79: Quiz automatizado con retroalimentación + acción remedial | K79: Diseño instruccional | M79: Pendiente
A80: R076 | B80: 5 | C80: =COUNTIFS($B$5:B80,B80) -> 6 | D80: Rise | E80: Rise M5-T3 · Supervisión humana y riesgos | F80: M5-AE3 | G80: =Estructura!N23 -> 105 | H80: Sí | I80: No | J80: Rise (pantallas) | K80: Diseño instruccional | M80: Pendiente
A81: R077 | B81: 5 | C81: =COUNTIFS($B$5:B81,B81) -> 7 | D81: Quiz formativo | E81: Quiz formativo M5-AE3 · Supervisión humana y riesgos | F81: M5-AE3 | G81: ='Parámetros'!$C$6 -> 15 | H81: Sí | I81: No | J81: Quiz automatizado con retroalimentación + acción remedial | K81: Diseño instruccional | M81: Pendiente
A82: R078 | B82: 5 | C82: =COUNTIFS($B$5:B82,B82) -> 8 | D82: Hito proyecto | E82: Proyecto aplicado · Hito 5: prototipo de automatización de un paso del proceso, con supervisión humana | F82: M5-AE2; M5-AE3 | G82: ='Parámetros'!$C$10 -> 90 | H82: Sí | I82: Sí | J82: Rise + actividad (caso) / entrega con rúbrica (hito) | K82: Diseño instruccional | M82: Pendiente
A83: R079 | B83: 5 | C83: =COUNTIFS($B$5:B83,B83) -> 9 | D83: Caso de aplicación | E83: Caso M5-C1 · Automatización de la atención al cliente con IA (Klarna) | F83: M5-AE1; M5-AE3 | G83: ='Parámetros'!$C$10 -> 90 | H83: Sí | I83: No | J83: Rise + actividad (caso) / entrega con rúbrica (hito) | K83: Diseño instruccional | M83: Pendiente
A84: R080 | B84: 5 | C84: =COUNTIFS($B$5:B84,B84) -> 10 | D84: Caso de aplicación | E84: Caso M5-C2 · Estrategia «AI-first» y sus efectos sobre el trabajo (Duolingo, 2025) | F84: M5-AE1; M5-AE3 | G84: ='Parámetros'!$C$10 -> 90 | H84: Sí | I84: No | J84: Rise + actividad (caso) / entrega con rúbrica (hito) | K84: Diseño instruccional | M84: Pendiente
A85: R081 | B85: 5 | C85: =COUNTIFS($B$5:B85,B85) -> 11 | D85: Foro | E85: Foro M5: discusión guiada del módulo (tutor responde en <24 h hábiles) | F85: M5-AE1; M5-AE2; M5-AE3 | G85: ='Parámetros'!$C$7 -> 30 | H85: Sí | I85: Sí | J85: Foro Moodle | K85: Diseño instruccional | M85: Pendiente
A86: R082 | B86: 5 | C86: =COUNTIFS($B$5:B86,B86) -> 12 | D86: Video | E86: Video de resumen M5 (3 min): ideas clave y conexión con el siguiente módulo | F86: — | G86: ='Parámetros'!$C$9 -> 3 | H86: Sí | I86: No | J86: Video con avatar/locución | K86: Diseño instruccional | M86: Pendiente
A87: R083 | B87: 5 | C87: =COUNTIFS($B$5:B87,B87) -> 13 | D87: Resumen y glosario | E87: Resumen y glosario del módulo M5 (página; lectura 1,5 min) | F87: — | G87: 1.5 | H87: Sí | I87: No | J87: Página Moodle | K87: Diseño instruccional | M87: Pendiente
A88: R084 | B88: 5 | C88: =COUNTIFS($B$5:B88,B88) -> 14 | D88: Complemento | E88: Infografía M5: Matriz impacto–riesgo para priorizar tareas a automatizar | F88: — | G88: 0 | H88: No | I88: No | J88: Infografía (imagen) | K88: Diseño instruccional | M88: Pendiente
A89: R085 | B89: 5 | C89: =COUNTIFS($B$5:B89,B89) -> 15 | D89: Evaluación sumativa | E89: Evaluación sumativa M5 | F89: M5-AE1; M5-AE2; M5-AE3 | G89: 45 | H89: Sí | I89: No | J89: Cuestionario Moodle con retroalimentación automática | K89: Diseño instruccional | M89: Pendiente
A90: R086 | B90: 6 | C90: =COUNTIFS($B$5:B90,B90) -> 1 | D90: Video | E90: Video de bienvenida M6 (3 min): qué aprenderás, cómo se evalúa, hito del proyecto | F90: — | G90: ='Parámetros'!$C$8 -> 3 | H90: Sí | I90: No | J90: Video con avatar/locución | K90: Diseño instruccional | M90: Pendiente
A91: R087 | B91: 6 | C91: =COUNTIFS($B$5:B91,B91) -> 2 | D91: Rise | E91: Rise M6-T1 · Oportunidad de mejora con IA | F91: M6-AE1 | G91: =Estructura!N24 -> 75 | H91: Sí | I91: No | J91: Rise (pantallas) | K91: Diseño instruccional | M91: Pendiente
A92: R088 | B92: 6 | C92: =COUNTIFS($B$5:B92,B92) -> 3 | D92: Quiz formativo | E92: Quiz formativo M6-AE1 · Oportunidad de mejora con IA | F92: M6-AE1 | G92: ='Parámetros'!$C$6 -> 15 | H92: Sí | I92: No | J92: Quiz automatizado con retroalimentación + acción remedial | K92: Diseño instruccional | M92: Pendiente
A93: R089 | B93: 6 | C93: =COUNTIFS($B$5:B93,B93) -> 4 | D93: Rise | E93: Rise M6-T2 · Implementar el flujo | F93: M6-AE2 | G93: =Estructura!N25 -> 75 | H93: Sí | I93: No | J93: Rise (pantallas) | K93: Diseño instruccional | M93: Pendiente
A94: R090 | B94: 6 | C94: =COUNTIFS($B$5:B94,B94) -> 5 | D94: Quiz formativo | E94: Quiz formativo M6-AE2 · Implementar el flujo | F94: M6-AE2 | G94: ='Parámetros'!$C$6 -> 15 | H94: Sí | I94: No | J94: Quiz automatizado con retroalimentación + acción remedial | K94: Diseño instruccional | M94: Pendiente
A95: R091 | B95: 6 | C95: =COUNTIFS($B$5:B95,B95) -> 6 | D95: Rise | E95: Rise M6-T3 · Resultados y aprendizajes | F95: M6-AE3 | G95: =Estructura!N26 -> 67.5 | H95: Sí | I95: No | J95: Rise (pantallas) | K95: Diseño instruccional | M95: Pendiente
A96: R092 | B96: 6 | C96: =COUNTIFS($B$5:B96,B96) -> 7 | D96: Quiz formativo | E96: Quiz formativo M6-AE3 · Resultados y aprendizajes | F96: M6-AE3 | G96: ='Parámetros'!$C$6 -> 15 | H96: Sí | I96: No | J96: Quiz automatizado con retroalimentación + acción remedial | K96: Diseño instruccional | M96: Pendiente
A97: R093 | B97: 6 | C97: =COUNTIFS($B$5:B97,B97) -> 8 | D97: Hito proyecto | E97: Proyecto aplicado · Hito 6a: diagnóstico, meta y plan de medición | F97: M6-AE1 | G97: ='Parámetros'!$C$10 -> 90 | H97: Sí | I97: Sí | J97: Rise + actividad (caso) / entrega con rúbrica (hito) | K97: Diseño instruccional | M97: Pendiente
A98: R094 | B98: 6 | C98: =COUNTIFS($B$5:B98,B98) -> 9 | D98: Hito proyecto | E98: Proyecto aplicado · Hito 6b: implementación del flujo | F98: M6-AE2 | G98: ='Parámetros'!$C$10 -> 90 | H98: Sí | I98: Sí | J98: Rise + actividad (caso) / entrega con rúbrica (hito) | K98: Diseño instruccional | M98: Pendiente
A99: R095 | B99: 6 | C99: =COUNTIFS($B$5:B99,B99) -> 10 | D99: Hito proyecto | E99: Proyecto aplicado · Hito 6c: medición de resultados y ajustes | F99: M6-AE3 | G99: ='Parámetros'!$C$10 -> 90 | H99: Sí | I99: Sí | J99: Rise + actividad (caso) / entrega con rúbrica (hito) | K99: Diseño instruccional | M99: Pendiente
A100: R096 | B100: 6 | C100: =COUNTIFS($B$5:B100,B100) -> 11 | D100: Hito proyecto | E100: Proyecto aplicado · Hito 6d: pitch y portafolio final (insumo del Demo Day) | F100: M6-AE3 | G100: ='Parámetros'!$C$10 -> 90 | H100: Sí | I100: Sí | J100: Rise + actividad (caso) / entrega con rúbrica (hito) | K100: Diseño instruccional | M100: Pendiente
A101: R097 | B101: 6 | C101: =COUNTIFS($B$5:B101,B101) -> 12 | D101: Foro | E101: Foro M6: discusión guiada del módulo (tutor responde en <24 h hábiles) | F101: M6-AE1; M6-AE2; M6-AE3 | G101: ='Parámetros'!$C$7 -> 30 | H101: Sí | I101: Sí | J101: Foro Moodle | K101: Diseño instruccional | M101: Pendiente
...

Sheet Casos y proyecto
A1: Casos de aplicación e hitos del proyecto incremental
A2: Casos con empresas reales (candidatos por verificar) y el proyecto que crece módulo a módulo hasta el pitch final.
A4: ID | B4: Módulo | C4: Tipo | D4: Título | E4: AE | F4: Descripción / qué documentar | G4: Fuente primaria (URL, fecha) | H4: Estado de verificación | I4: Entregable | J4: Retroalimentación tutor
A5: M1-P1 | B5: 1 | C5: Hito proyecto | D5: Proyecto aplicado · Hito 1: problema u oportunidad real + biblioteca de prompts v1 | E5: M1-AE1; M1-AE2 | F5: Cada participante elige un desafío laboral real: una tarea de un cargo que ejerce o al que aspira (tomada de una oferta real) y arma su primera biblioteca de prompts para resolverla. Entregable con retroalimentación del tutor (≤72 h). | H5: No aplica | I5: Entrega con rúbrica general (ver «Evaluación») | J5: ≤72 h (hábiles a definir)
A6: M1-C1 | B6: 1 | C6: Caso de aplicación | D6: Caso M1-C1 · Asistente de IA para asesores financieros (Morgan Stanley) | E6: M1-AE2; M1-AE3 | F6: Candidato. Documentar: qué prompts/instrucciones se usan, qué fuentes consulta el asistente, cómo se controla la calidad. POR VERIFICAR en fuente primaria (comunicados de la empresa y de OpenAI). | H6: Por verificar | I6: Actividad de análisis del caso: preguntas guiadas + aplicación al proyecto (1,5 h) | J6: Autocorrección + foro
A7: M1-C2 | B7: 1 | C7: Caso de aplicación | D7: Caso M1-C2 · Cuando la IA inventa: abogados y jurisprudencia inexistente (Mata v. Avianca, 2023) y chatbot de Air Canada (2024) | E7: M1-AE4 | F7: Candidato. Documentar: qué se verificó o no, consecuencias. POR VERIFICAR en fuente primaria (resoluciones judiciales / del tribunal). | H7: Por verificar | I7: Actividad de análisis del caso: preguntas guiadas + aplicación al proyecto (1,5 h) | J7: Autocorrección + foro
A8: M2-P2 | B8: 2 | C8: Hito proyecto | D8: Proyecto aplicado · Hito 2: brief del proyecto + presentación de 6 láminas | E8: M2-AE1; M2-AE3 | F8: El problema del Hito 1 se convierte en un brief (objetivo, audiencia, mensaje) y una presentación de 6 láminas con IA. Retroalimentación del tutor (≤72 h). | H8: No aplica | I8: Entrega con rúbrica general (ver «Evaluación») | J8: ≤72 h (hábiles a definir)
A9: M2-C1 | B9: 2 | C9: Caso de aplicación | D9: Caso M2-C1 · Comunicación con clientes redactada con apoyo de IA (Octopus Energy) | E9: M2-AE1; M2-AE2 | F9: Candidato. Documentar el uso de IA para respuestas a clientes y cómo se supervisa. POR VERIFICAR en fuente primaria/prensa de calidad, con fecha. | H9: Por verificar | I9: Actividad de análisis del caso: preguntas guiadas + aplicación al proyecto (1,5 h) | J9: Autocorrección + foro
A10: M2-C2 | B10: 2 | C10: Caso de aplicación | D10: Caso M2-C2 · Asistente de IA en herramientas de oficina para equipos (Vodafone y Microsoft 365 Copilot) | E10: M2-AE3; M2-AE4 | F10: Candidato. Documentar tareas de oficina asistidas (documentos, presentaciones, planillas). POR VERIFICAR: no usar cifras sin fuente primaria. | H10: Por verificar | I10: Actividad de análisis del caso: preguntas guiadas + aplicación al proyecto (1,5 h) | J10: Autocorrección + foro
A11: M3-P3 | B11: 3 | C11: Hito proyecto | D11: Proyecto aplicado · Hito 3: investigación validada con fuentes (informe breve) | E11: M3-AE1; M3-AE3 | F11: Investigación sobre el problema del proyecto con fuentes contrastadas y citadas. Retroalimentación del tutor (≤72 h). | H11: No aplica | I11: Entrega con rúbrica general (ver «Evaluación») | J11: ≤72 h (hábiles a definir)
A12: M3-C1 | B12: 3 | C12: Caso de aplicación | D12: Caso M3-C1 · Informe con referencias inexistentes generadas por IA (Deloitte Australia, 2025) | E12: M3-AE2; M3-AE4 | F12: Candidato. Documentar qué falló en la validación de fuentes y qué medidas se tomaron. POR VERIFICAR en fuente primaria (prensa de calidad y comunicado oficial). | H12: Por verificar | I12: Actividad de análisis del caso: preguntas guiadas + aplicación al proyecto (1,5 h) | J12: Autocorrección + foro
A13: M3-C2 | B13: 3 | C13: Caso de aplicación | D13: Caso M3-C2 · Información confidencial ingresada a una herramienta de IA (Samsung, 2023) | E13: M3-AE4 | F13: Candidato. Documentar el incidente y las políticas posteriores. POR VERIFICAR en fuente primaria. | H13: Por verificar | I13: Actividad de análisis del caso: preguntas guiadas + aplicación al proyecto (1,5 h) | J13: Autocorrección + foro
A14: M4-P4 | B14: 4 | C14: Hito proyecto | D14: Proyecto aplicado · Hito 4: pieza multimedia que comunica la solución | E14: M4-AE2; M4-AE4 | F14: Pieza visual, sonora o audiovisual (con ficha de uso ético) que comunica la propuesta del proyecto. Retroalimentación del tutor (≤72 h). | H14: No aplica | I14: Entrega con rúbrica general (ver «Evaluación») | J14: ≤72 h (hábiles a definir)
A15: M4-C1 | B15: 4 | C15: Caso de aplicación | D15: Caso M4-C1 · Campañas de marca hechas con IA generativa (Coca-Cola, 2023 y 2024) | E15: M4-AE2; M4-AE4 | F15: Candidato. Documentar proceso, herramientas y reacciones del público. POR VERIFICAR en fuentes primarias y de prensa. | H15: Por verificar | I15: Actividad de análisis del caso: preguntas guiadas + aplicación al proyecto (1,5 h) | J15: Autocorrección + foro
A16: M4-C2 | B16: 4 | C16: Caso de aplicación | D16: Caso M4-C2 · Voz sintética y consentimiento (disputa Scarlett Johansson – OpenAI, 2024) | E16: M4-AE3 | F16: Candidato. Documentar la disputa y la decisión de la empresa. POR VERIFICAR en fuente primaria. | H16: Por verificar | I16: Actividad de análisis del caso: preguntas guiadas + aplicación al proyecto (1,5 h) | J16: Autocorrección + foro
... A24: M6-P6d | B24: 6 | C24: Hito proyecto | D24: Proyecto aplicado · Hito 6d: pitch y portafolio final (insumo del Demo Day) | E24: M6-AE3 | F24: Pitch de 3 min y portafolio. Retroalimentación del tutor (≤72 h). | H24: No aplica | I24: Entrega con rúbrica general (ver «Evaluación») | J24: ≤72 h (hábiles a definir)
A26: Hilo del proyecto aplicado
A27: M1 | B27: Definir el problema u oportunidad real + primera biblioteca de prompts
A28: M2 | B28: Convertirlo en un brief y una presentación de 6 láminas
A29: M3 | B29: Respaldarlo con una investigación validada con fuentes
A30: M4 | B30: Comunicarlo con una pieza multimedia con ficha de uso ético
A31: M5 | B31: Automatizar un paso del proceso con supervisión humana
A32: M6 | B32: Diagnosticar metas, implementar, medir y presentar (pitch + portafolio; conecta con el Demo Day)

Sheet Evaluación
A1: Sistema de evaluación (propuesta inicial)
A2: Provisional: la norma de evaluación definitiva debe alinearse con la normativa SENCE vigente al presentar.
A4: Instrumento | B4: Cantidad | C4: Tipo | D4: Momento | E4: Retroalimentación | F4: Ponderación c/u | G4: Ponderación total | H4: Observación
A5: Evaluación diagnóstica | B5: 1 | C5: Diagnóstica | D5: Inicio del curso (M1) | E5: Automática; orienta la ruta de estudio | F5: 0 | G5: =B5*F5 -> 0 | H5: No pondera.
A6: Quizzes formativos por tema | B6: 22 | C6: Formativa | D6: Cierre de cada tema | E6: Automática por ítem + acción remedial (volver a pantallas específicas) | F6: 0 | G6: =B6*F6 -> 0 | H6: No pondera; condiciona el avance sugerido.
A7: Evaluaciones sumativas M1–M5 | B7: 5 | C7: Sumativa | D7: Cierre de cada módulo | E7: Automática con retroalimentación por pregunta | F7: 0.08 | G7: =B7*F7 -> 0.4 | H7: Banco de ítems con distintos tipos de pregunta.
A8: Hitos del proyecto M1–M5 (con rúbrica) | B8: 5 | C8: Sumativa | D8: Cierre de cada módulo | E8: Tutor, ≤72 h, con rúbrica | F8: 0.03 | G8: =B8*F8 -> 0.15 | H8: Instancia obligatoria de interacción pedagógica (Ley 21.850).
A9: Hitos de proceso M6 (6a, 6b, 6c) | B9: 3 | C9: Formativa | D9: Módulo 6 | E9: Tutor, ≤72 h, con rúbrica | F9: 0 | G9: =B9*F9 -> 0 | H9: No ponderan; alimentan el hito final.
A10: Pitch + portafolio final (hito 6d) | B10: 1 | C10: Sumativa | D10: Cierre del curso | E10: Tutor, ≤72 h, con rúbrica | F10: 0.15 | G10: =B10*F10 -> 0.15 | H10: Insumo del Demo Day.
A11: Evaluación final integradora | B11: 1 | C11: Sumativa | D11: Cierre del curso | E11: Automática con retroalimentación por pregunta | F11: 0.3 | G11: =B11*F11 -> 0.3 | H11: Cubre los 22 AE; varios tipos de pregunta.
A12: Total ponderación | G12: =SUM(G5:G11) -> 1 | H12: =IF(ROUND(G12,4)=1,"OK: suma 100%","Revisar: debe sumar 100%") -> OK: suma 100%
A14: Norma de evaluación (a confirmar)
A15: Escala | B15: 1,0 a 7,0
A16: Nota mínima de aprobación | B16: 4,0 (exigencia 60%) — PROVISIONAL
A17: Aprobación académica | B17: Se define por la nota final ponderada, no por el porcentaje de conectividad. El registro de participación SENCE (conectividad con Clave Única) es un requisito distinto, de ejecución.
A18: Evaluaciones que rinden | B18: Diagnóstica, 22 quizzes formativos, 5 sumativas de módulo, 5 hitos con rúbrica, pitch final y evaluación final integradora
A20: Rúbrica general de hitos del proyecto
A21: Criterio | B21: Peso | C21: Logrado (100%) | D21: Parcial (60%) | E21: No logrado (0%)
A22: Pertinencia al problema real | B22: 0.25 | C22: El entregable resuelve con claridad el problema definido. | D22: Resuelve parcialmente o con ambigüedad. | E22: No se relaciona con el problema.
A23: Uso verificado de IA | B23: 0.25 | C23: Documenta prompts y valida resultados con fuentes. | D23: Valida solo en parte o documenta poco. | E23: No valida ni documenta.
A24: Calidad del entregable | B24: 0.2 | C24: Completo, ordenado y sin errores relevantes. | D24: Completo con errores menores. | E24: Incompleto o con errores graves.
A25: Ética, privacidad y licencias | B25: 0.15 | C25: Resguarda datos y respeta licencias y consentimiento. | D25: Cumple con omisiones menores. | E25: Expone datos o infringe licencias.
A26: Comunicación | B26: 0.15 | C26: Mensaje claro, adecuado a la audiencia. | D26: Mensaje comprensible pero poco ajustado. | E26: Mensaje confuso.
A27: Total | B27: =SUM(B22:B26) -> 1 | C27: =IF(ROUND(B27,4)=1,"OK: suma 100%","Revisar") -> OK: suma 100%

Sheet Cumplimiento RE 2484
A1: Cumplimiento de la RE 2.484 (19-10-2026) · Instructivo de solicitudes de curso FT
A2: Cada exigencia (paráfrasis fiel del texto) cruzada con el diseño. La evaluación técnica depende del Anexo Técnico, que no está en el documento.
A4: # | B4: Sección RE 2.484 | C4: Etapa | D4: Exigencia | E4: Cómo la cubre este diseño | F4: Dónde verificarlo | G4: Verificación automática | H4: Estado | I4: Riesgo
A5: 1 | B5: IV.2.1 a) | C5: Admisibilidad legal | D5: La actividad tiene finalidad formativa orientada a conocimientos, habilidades o competencias ligadas al trabajo y a la empleabilidad, productividad, adaptación tecnológica o desempeño laboral. | E5: Competencias y AE formulados sobre tareas laborales; proyecto basado en un desafío laboral real (cargo actual o aspirado); público cesante y en actividad. | F5: Estructura (competencia, AE) | G5: — | H5: Cubierto en diseño | I5: Bajo
A6: 2 | B6: IV.2.1 b) | C6: Admisibilidad legal | D6: Nombre, competencia, AE y contenidos no corresponden a una actividad recreativa, de esparcimiento, integración o bienestar. | E6: Nombre «IA generativa para entornos laborales»; AE con verbos de aplicación y condiciones laborales. | F6: Estructura | G6: — | H6: Cubierto en diseño | I6: Bajo
A7: 3 | B7: IV.2.1 c) | C7: Admisibilidad legal | D7: Hay un proceso de aprendizaje estructurado; no consiste solo en entregar o revisar contenidos de forma autónoma. | E7: Cada tema combina Rise + quiz; cada módulo suma casos/hitos con retroalimentación, foro y evaluación sumativa. | F7: Recursos (tipos Caso, Hito, Foro, Quiz) | G7: =COUNTIFS(Recursos!$D$5:$D$200,"Hito proyecto")+COUNTIFS(Recursos!$D$5:$D$200,"Caso de aplicación")+COUNTIFS(Recursos!$D$5:$D$200,"Foro")&" actividades de aplicación/interacción" -> 26 actividades de aplicación/interacción | H7: Cubierto en diseño | I7: Medio
A8: 4 | B8: IV.2.1 d) | C8: Admisibilidad legal | D8: La actividad no es una formalidad administrativa o normativa sin propósito efectivo de aprendizaje. | E8: Curso de desarrollo de competencias, sin carácter de trámite. | F8: Estructura | G8: — | H8: Cubierto en diseño | I8: Bajo
A9: 5 | B9: IV.2.1 e) y II.2 | C9: Admisibilidad legal | D9: Duración en horas cronológicas, mínimo 8 h, proporcional a competencias, AE, contenidos y técnicas; se debe calibrar considerando la taxonomía de Bloom y el área de la capacitación. | E9: 88 h con distribución justificada: ≈48% estudio, ≈34% aplicación (más Bloom alto en aplicar/evaluar/crear). Ver Matriz coherencia (nivel Bloom por AE). | F9: Parámetros (horas totales); Resumen horas | G9: =IF('Parámetros'!$C$12>=8,"≥ 8 h: cumple mínimo","Bajo el mínimo") -> ≥ 8 h: cumple mínimo | H9: Por definir | I9: Medio
A10: 6 | B10: IV.2.1 f) y II.1.b.2 | C10: Admisibilidad legal | D10: Existe una persona facilitadora, tutora o responsable del proceso formativo; en asincrónica se verifica la intervención efectiva de un facilitador responsable. | E10: Hitos con retroalimentación, foros con respuesta del tutor (<24 h hábiles) y seguimiento. FALTA identificar al facilitador/tutor responsable. | F10: Recursos (columna Interacción facilitador/tutor) | G10: =COUNTIFS(Recursos!$I$5:$I$200,"Sí")&" recursos con intervención del facilitador" -> 15 recursos con intervención del facilitador | H10: Por definir | I10: Alto
A11: 7 | B11: IV.2.1 g) | C11: Admisibilidad legal | D11: Contempla al menos una instancia obligatoria de interacción, retroalimentación o acompañamiento vinculada al aprendizaje (misma exigencia de la Ley 21.850 art. 29 N°1). | E11: 9 hitos del proyecto con retroalimentación del facilitador (≤72 h) y 6 foros moderados; los hitos son obligatorios y evaluados. | F11: Recursos; Casos y proyecto | G11: =COUNTIFS(Recursos!$D$5:$D$200,"Hito proyecto")&" hitos + "&COUNTIFS(Recursos!$D$5:$D$200,"Foro")&" foros" -> 9 hitos + 6 foros | H11: Cubierto en diseño | I11: Alto
A12: 8 | B12: IV.2.1 h) | C12: Admisibilidad legal | D12: Contiene una evaluación destinada a verificar los aprendizajes logrados. | E12: Diagnóstica, 22 quizzes formativos, 6 evaluaciones sumativas (la última integradora), hitos con rúbrica. | F12: Evaluación; Recursos | G12: =COUNTIFS(Recursos!$D$5:$D$200,"Evaluación sumativa")&" evaluaciones sumativas" -> 6 evaluaciones sumativas | H12: Cubierto en diseño | I12: Alto
A13: 9 | B13: IV.2.1 (cierre) | C13: Admisibilidad legal | D13: Incumplir cualquiera de las exigencias a)–h) hace la solicitud inadmisible y no se continúa la revisión. | E13: Revisar las ocho filas anteriores antes de ingresar; las marcadas «Por definir» deben cerrarse. | F13: — | G13: — | H13: Por definir | I13: Alto
A14: 10 | B14: IV.2.2 a) | C14: Admisibilidad formal | D14: Todos los campos y antecedentes obligatorios del sistema están completos. | E14: Se completará con las hojas Estructura, Recursos y Evaluación como fuente única. | F14: Estructura, Recursos | G14: — | H14: Por definir | I14: Medio
A15: 11 | B15: IV.2.2 b) | C15: Admisibilidad formal | D15: Competencia, AE, contenidos, técnicas metodológicas, actividades y mecanismos de evaluación son coherentes y consistentes entre sí. | E15: Matriz de coherencia: cada AE con contenidos, técnica, actividades, criterios e instrumentos; cobertura verificada por fórmula. | F15: Matriz coherencia | G15: =COUNTIF(Estructura!$T$5:$T$26,"OK")&" de 22 AE con cobertura completa" -> 22 de 22 AE con cobertura completa | H15: Cubierto en diseño | I15: Alto
A16: 12 | B16: IV.2.2 c) | C16: Admisibilidad formal | D16: La duración total está bien declarada y concuerda con el desglose horario de las actividades formativas. | E16: El desglose suma exactamente 88 h (diferencia 0 min por módulo). | F16: Resumen horas | G16: =IF(ROUND('Resumen horas'!O11,1)=0,"Desglose = duración total","Diferencia: "&TEXT('Resumen horas'!O11,"0.0")&" min") -> Desglose = duración total | H16: Cubierto en diseño | I16: Alto
A17: 13 | B17: IV.2.2 d) y II.1.b.2 | C17: Admisibilidad formal | D17: La modalidad está correctamente identificada: a distancia o e-learning, asincrónica (no requiere conexión simultánea; ritmos personalizados) y ejecutada en una LMS. | E17: Declarar «A distancia o e-learning – asincrónica» en Moodle. No es autoaprendizaje sin LMS. | F17: Léeme | G17: — | H17: Cubierto en diseño | I17: Alto
A18: 14 | B18: IV.2.2 e) | C18: Admisibilidad formal | D18: Los antecedentes no contienen contradicciones, inconsistencias manifiestas ni información insuficiente. | E18: Revisión cruzada final entre propuesta comercial, solicitud y aula (nombre, horas, modalidad, facilitador). | F18: — | G18: — | H18: Por definir | I18: Medio
A19: 15 | B19: IV.3 a) | C19: Evaluación técnica | D19: Coherencia curricular: relación entre nombre del curso, competencia, AE, contenidos y características de los participantes. | E19: Participantes: cesantes principalmente y personas en actividad; AE y proyecto funcionan para ambos perfiles. | F19: Léeme; Estructura | G19: — | H19: Depende del Anexo Técnico | I19: Medio
A20: 16 | B20: IV.3 b) | C20: Evaluación técnica | D20: Pertinencia y suficiencia de las técnicas metodológicas para lograr los AE y adecuación a la modalidad. | E20: Una técnica por AE (práctica guiada, laboratorio, casos reales, proyecto con retroalimentación). | F20: Estructura (columna Técnica) | G20: — | H20: Depende del Anexo Técnico | I20: Medio
A21: 17 | B21: IV.3 c) | C21: Evaluación técnica | D21: Suficiencia y proporcionalidad de la duración, incluida su distribución entre actividades. | E21: Distribución por tipo de actividad y por módulo, con parámetros explícitos (7,5 min/pantalla, etc.). | F21: Resumen horas; Parámetros | G21: — | H21: Depende del Anexo Técnico | I21: Medio
A22: 18 | B22: IV.3 d) y II.1.b.2 | C22: Evaluación técnica | D22: Presencia de las competencias del facilitador/tutor para conducir, orientar y apoyar el aprendizaje. | E22: Perfil por definir (IA generativa aplicada + tutoría e-learning). | F22: Pendientes | G22: — | H22: Por definir | I22: Alto
A23: 19 | B23: IV.3 e) | C23: Evaluación técnica | D23: Existencia y suficiencia de mecanismos de interacción, retroalimentación o acompañamiento que formen parte efectiva del aprendizaje, no una mera disponibilidad formal. | E23: Hitos obligatorios y evaluados, foros con participación del tutor, retroalimentación en plazo definido. | F23: Recursos; Casos y proyecto | G23: — | H23: Depende del Anexo Técnico | I23: Alto
A24: 20 | B24: IV.3 f) | C24: Evaluación técnica | D24: Pertinencia de la estrategia e instrumentos de evaluación y su correspondencia con competencia, AE y contenidos. | E24: Criterios de evaluación por AE e instrumentos en la Matriz de coherencia; norma de aprobación en la hoja Evaluación. | F24: Matriz coherencia; Evaluación | G24: — | H24: Depende del Anexo Técnico | I24: Alto
A25: 21 | B25: IV.3 g) | C25: Evaluación técnica | D25: Adecuación de materiales didácticos, recursos, infraestructura, equipamiento y plataformas según naturaleza, metodología, modalidad y número de participantes. | E25: Moodle con Rise (SCORM), quizzes, foros, videos; herramientas de IA con plan gratuito; confirmar capacidad para 100 participantes. | F25: Recursos | G25: — | H25: Depende del Anexo Técnico | I25: Medio
A26: 22 | B26: III.2 | C26: Operativa | D26: La LMS es el entorno de ejecución y registro; SENCE puede revisarla y el acceso debe mantenerse operativo durante la revisión y toda la vigencia del curso. | E26: Entregar accesos de revisión; curso completo en Moodle antes de presentar; compromiso de mantener la plataforma. | F26: Pendientes | G26: — | H26: Por definir | I26: Alto
A27: 23 | B27: III.2 | C27: Operativa | D27: Trazabilidad: registros de identificación y participación, progresión, actividades realizadas, intervención del facilitador, interacciones/retroalimentaciones, y evaluaciones con sus resultados; deben permitir reconstruir el proceso. | E27: Activar finalización de actividades, registros, foros, comentarios de retroalimentación y libro de calificaciones en Moodle. | F27: Pendientes | G27: — | H27: Por definir | I27: Alto
A28: 24 | B28: IV.3.1 | C28: Operativa | D28: Costos en pesos coherentes con modalidad, participantes, duración, plataforma, facilitadores, materiales y evaluación; SENCE puede observar inconsistencias. | E28: Armar el desglose de costos con la hoja Recursos como respaldo. | F28: — | G28: — | H28: Por definir | I28: Medio
... A33: 29 | B33: VI.2 | C33: Operativa | D33: Las modificaciones excepcionales se piden por Buzón Ciudadano y no pueden alterar la identidad del curso ni sustituir al facilitador autorizado. | E33: Definir bien el facilitador y la estructura desde el inicio. | F33: Pendientes | G33: — | H33: Por definir | I33: Alto
D35: Resumen de estado
D36: Cubierto en diseño | E36: =COUNTIF($H$5:$H$33,D36) -> 9
D37: Por definir | E37: =COUNTIF($H$5:$H$33,D37) -> 14
D38: Depende del Anexo Técnico | E38: =COUNTIF($H$5:$H$33,D38) -> 6
D39: Verificado en Moodle | E39: =COUNTIF($H$5:$H$33,D39) -> 0

Sheet Pendientes
A1: Pendientes y decisiones abiertas
A2: Qué falta para pasar de borrador a estructura definitiva.
A4: # | B4: Pendiente | C4: Por qué importa | D4: Quién | E4: Estado
A5: 1 | B5: Revisar la pertinencia de los 22 AE, las competencias y los contenidos con quien valide el contenido (módulos y temas de la propuesta). | C5: PF1823 es solo referencia; lo que importa es que cada AE sea pertinente al tema, medible y que suba en complejidad dentro del módulo. | D5: Naty | E5: Pendiente
A6: 2 | B6: Localizar fuente primaria de cada caso candidato (URL y fecha) y descartar los que no se puedan respaldar. | C6: Los casos deben ser reales, documentados y citados; no se usan cifras sin respaldo. | D6: Diseño instruccional | E6: Pendiente
A7: 3 | B7: OBTENER el Anexo Técnico (criterios, indicadores, medios de verificación y estándares) y la Guía Técnica de Presentación, Revisión y Autorización que cita la RE 2.484 (IV.3 y IV.5). | C7: La RE 2.484 delega ahí la evaluación técnica. No vienen en el PDF de la resolución y no los encontré en sence.cl al 22-10-2026 (la página para OTEC aún lista solo documentos anteriores). Sin ellos no se puede garantizar la aprobación a la primera. Vía: sence.cl, Buzón Ciudadano o comunicación a OTEC. | D7: Naty | E7: Pendiente
A8: 4 | B8: Decidir si la solicitud se presenta vinculada a un Plan Formativo (PF1823) o como curso independiente. | C8: RE 2.484 II.2.1: si deriva de un Plan Formativo, la duración queda fijada por él y SENCE verifica que las horas coincidan. Si es independiente, las 88 h deben justificarse por proporcionalidad y taxonomía de Bloom (II.2). Cambia cómo se declara la duración. | D8: Naty | E8: Pendiente
A9: 5 | B9: Definir el facilitador/tutor responsable (nombre, perfil y competencias) y su carga con 100 participantes. | C9: RE 2.484 VI.2: el facilitador informado y autorizado NO puede modificarse ni sustituirse durante la vigencia (4 años); IV.2.1 f) y IV.3 d) exigen su presencia y competencias. Confirmar en la plataforma si se pueden declarar varios y qué ocurre ante ausencia. | D9: Naty | E9: Pendiente
A10: 6 | B10: Plazos: la revisión toma hasta 20 días corridos desde la presentación y se reinicia ÍNTEGRA con cada reingreso; luego hay 20 días corridos para pagar la inscripción. | C10: RE 2.484 IV.1.1 y V.1. Si se presenta el 23-oct, la respuesta llegaría hasta el 12-nov sin observaciones; una sola observación haría imposible el inicio del 23-nov. Evaluar presentar de inmediato y con todo el material ya cargado. | D10: Naty | E10: Pendiente
A11: 7 | B11: Dejar el curso completo y operativo en el Moodle ANTES de presentar y dar acceso de revisión a SENCE. | C11: RE 2.484 III.2: SENCE puede revisar la plataforma y el acceso debe mantenerse operativo durante la revisión y toda la vigencia del curso. Esto adelanta la producción de Rise, quizzes, foros y evaluaciones. | D11: Equipo producción | E11: Pendiente
A12: 8 | B12: Configurar en Moodle la trazabilidad exigida: identificación y participación, progresión, actividades realizadas, intervenciones del facilitador, interacciones/retroalimentaciones, evaluaciones y resultados. | C12: RE 2.484 III.2 pide poder reconstruir el proceso formativo con esos registros. Hay que dejar activos finalización de actividades, registros, foros con participación del tutor, comentarios de retroalimentación y libro de calificaciones. | D12: Equipo producción | E12: Pendiente
A13: 9 | B13: Declarar costos en pesos coherentes con la modalidad, duración, plataforma, facilitador y materiales. | C13: RE 2.484 IV.3.1: SENCE puede observar costos inconsistentes u omitidos. | D13: Naty | E13: Pendiente
A14: 10 | B14: Revisar RE 2.486 (procedimiento transitorio de adecuación) cuando se publique su texto. | C14: Aplica a cursos ya inscritos; no a una solicitud nueva, pero conviene confirmar. | D14: Naty | E14: Pendiente
A15: 11 | B15: La planilla «Checklist_codigo_SENCE_asincronico» está construida sobre la RE 1560 (derogada). Rehacerla sobre la RE 2.484 y el Anexo Técnico cuando lo tengamos. | C15: Hoy el cruce con la norma vigente está en la hoja «Cumplimiento RE 2484» de este libro. | D15: Claude | E15: Pendiente
A16: 12 | B16: Definir la instancia de interacción pedagógica del tutor (frecuencia, plazo, registro) para cumplir la Ley 21.850. | C16: Los hitos con retroalimentación (≤72 h) la cubren en esta propuesta; falta fijar plazo en días hábiles y evidencia de registro. | D16: Naty | E16: Pendiente
... A22: 18 | B22: Nota de coherencia: el total de bloques de aplicación (casos + hitos) es 20 (11 casos + 9 hitos), es decir 30 h. Un resumen anterior hablaba de 24. | C22: Corrección del conteo; los totales de horas de esta hoja son los que valen. | D22: — | E22: Pendiente
